Workbook

Sheet Instructions

Sheet निर्देश

Sheet Input
E2: EPS 1995 Pension - Input
E3: Developed by Mr. Neeraj Bhargava (9950826109) in consultation with Mr. Parveen Kohli (9810306699) & with technical support from Mr. C Ramasamy
E5: Please read Instructions given in INSTRUCTIONS sheet carefully before proceeding for filling Input Sheet, else the results may differ from Actuals
E7: Fill data from existing PPO for Verifying / Calculating "Ceiling Salary Pension" (Format for Dates : DD-MM-YYYY) | O7: Fill data for Calculating "Actual Salary Pension"
E8: Date of Birth | I8: 22386 | J8: Name | K8: VARRINDER KAUR RAINA | O8: Date of commencement of Actual Salary Pension (Format: DD-MM-YYYY)
E9: Date of Joining PF | I9: 29221 | J9: Non Contributory Period, if any (nos. in Days) | N9: 0
E10: Date of Exit | I10: 43586 | J10: Last month when full salary received | L10: 44287 | M10: Service Weightage (in years) | N10: 39
E11: Date of commencement of "Ceiling Amount Pension" | I11: 43586 | O11: 43586
E13: S No | F13: Financial Year | G13: Input data for Monthly PF'able salary
G14: Please fill PF'able Salary is considered like, 16th November to 30th November amount to be transferred in December month, December amount paid in January and likewise | O14: 01-12-1995 (16/11-30/11)
E15: 1 | F15: 1995-96 | G15: 34790 | H15: 34820 | I15: 34851 | J15: 34881 | K15: 34912 | L15: 34943 | M15: 34973 | N15: 35004 | O15: 35034 | P15: 35065 | Q15: 35096 | R15: 35125
G16: EPS-95 started from 16-11-1995
E17: 2 | F17: 1996-97 | G17: 35156 | H17: 35186 | I17: 35217 | J17: 35247 | K17: 35278 | L17: 35309 | M17: 35339 | N17: 35370 | O17: 35400 | P17: 35431 | Q17: 35462 | R17: 35490
E19: 3 | F19: 1997-98 | G19: 35521 | H19: 35551 | I19: 35582 | J19: 35612 | K19: 35643 | L19: 35674 | M19: 35704 | N19: 35735 | O19: 35765 | P19: 35796 | Q19: 35827 | R19: 35855
E21: 4 | F21: 1998-99 | G21: 35886 | H21: 35916 | I21: 35947 | J21: 35977 | K21: 36008 | L21: 36039 | M21: 36069 | N21: 36100 | O21: 36130 | P21: 36161 | Q21: 36192 | R21: 36220
E23: 5 | F23: 1999-2000 | G23: 36251 | H23: 36281 | I23: 36312 | J23: 36342 | K23: 36373 | L23: 36404 | M23: 36434 | N23: 36465 | O23: 36495 | P23: 36526 | Q23: 36557 | R23: 36586
E25: 6 | F25: 2000-01 | G25: 36617 | H25: 36647 | I25: 36678 | J25: 36708 | K25: 36739 | L25: 36770 | M25: 36800 | N25: 36831 | O25: 36861 | P25: 36892 | Q25: 36923 | R25: 36951
E27: 7 | F27: 2001-02 | G27: 36982 | H27: 37012 | I27: 37043 | J27: 37073 | K27: 37104 | L27: 37135 | M27: 37165 | N27: 37196 | O27: 37226 | P27: 37257 | Q27: 37288 | R27: 37316
E29: 8 | F29: 2002-03 | G29: 37347 | H29: 37377 | I29: 37408 | J29: 37438 | K29: 37469 | L29: 37500 | M29: 37530 | N29: 37561 | O29: 37591 | P29: 37622 | Q29: 37653 | R29: 37681
E31: 9 | F31: 2003-04 | G31: 37712 | H31: 37742 | I31: 37773 | J31: 37803 | K31: 37834 | L31: 37865 | M31: 37895 | N31: 37926 | O31: 37956 | P31: 37987 | Q31: 38018 | R31: 38047
E33: 10 | F33: 2004-05 | G33: 38078 | H33: 38108 | I33: 38139 | J33: 38169 | K33: 38200 | L33: 38231 | M33: 38261 | N33: 38292 | O33: 38322 | P33: 38353 | Q33: 38384 | R33: 38412
E35: 11 | F35: 2005-06 | G35: 38443 | H35: 38473 | I35: 38504 | J35: 38534 | K35: 38565 | L35: 38596 | M35: 38626 | N35: 38657 | O35: 38687 | P35: 38718 | Q35: 38749 | R35: 38777
E37: 12 | F37: 2006-07 | G37: 38808 | H37: 38838 | I37: 38869 | J37: 38899 | K37: 38930 | L37: 38961 | M37: 38991 | N37: 39022 | O37: 39052 | P37: 39083 | Q37: 39114 | R37: 39142
E39: 13 | F39: 2007-08 | G39: 39173 | H39: 39203 | I39: 39234 | J39: 39264 | K39: 39295 | L39: 39326 | M39: 39356 | N39: 39387 | O39: 39417 | P39: 39448 | Q39: 39479 | R39: 39508
E41: 14 | F41: 2008-09 | G41: 39539 | H41: 39569 | I41: 39600 | J41: 39630 | K41: 39661 | L41: 39692 | M41: 39722 | N41: 39753 | O41: 39783 | P41: 39814 | Q41: 39845 | R41: 39873
R42: 174178
E43: 15 | F43: 2009-10 | G43: 39904 | H43: 39934 | I43: 39965 | J43: 39995 | K43: 40026 | L43: 40057 | M43: 40087 | N43: 40118 | O43: 40148 | P43: 40179 | Q43: 40210 | R43: 40238
G44: 28963 | H44: 28963 | I44: 31813 | J44: 29841 | K44: 29841 | L44: 29841 | M44: 31064 | N44: 31064 | O44: 34721 | P44: 31052 | Q44: 31052 | R44: 31052
E45: 16 | F45: 2010-11 | G45: 40269 | H45: 40299 | I45: 40330 | J45: 40360 | K45: 40391 | L45: 40422 | M45: 40452 | N45: 40483 | O45: 40513 | P45: 40544 | Q45: 40575 | R45: 40603
G46: 38876 | H46: 33008 | I46: 33008 | J46: 33008 | K46: 33008 | L46: 35774 | M46: 41488 | N46: 36598 | O46: 36598 | P46: 36598 | Q46: 36598 | R46: 54870
E47: 17 | F47: 2011-12 | G47: 40634 | H47: 40664 | I47: 40695 | J47: 40725 | K47: 40756 | L47: 40787 | M47: 40817 | N47: 40848 | O47: 40878 | P47: 40909 | Q47: 40940 | R47: 40969
G48: 41140 | H48: 38112 | I48: 38112 | J48: 39260 | K48: 39260 | L48: 39260 | M48: 41080 | N48: 41080 | O48: 46540 | P48: 41080 | Q48: 41080 | R48: 41080
E49: 18 | F49: 2012-13 | G49: 41000 | H49: 41030 | I49: 41061 | J49: 41091 | K49: 41122 | L49: 41153 | M49: 41183 | N49: 41214 | O49: 41244 | P49: 41275 | Q49: 41306 | R49: 41334
G50: 42900 | H50: 42900 | I50: 48360 | J50: 44187 | K50: 44187 | L50: 44187 | M50: 46062 | N50: 51687 | O50: 46062 | P50: 46062 | Q50: 46062 | R50: 46062
E51: 19 | F51: 2013-14 | G51: 41365 | H51: 41395 | I51: 41426 | J51: 41456 | K51: 41487 | L51: 41518 | M51: 41548 | N51: 41579 | O51: 41609 | P51: 41640 | Q51: 41671 | R51: 41699
G52: 46062 | H52: 56772 | I52: 48204 | J52: 49662 | K52: 49662 | L52: 57939 | M52: 52421 | N52: 52421 | O52: 52421 | P52: 52421 | Q52: 52421 | R52: 52421
E53: 20 | F53: 2014-15 | G53: 41730 | H53: 41760 | I53: 41791 | J53: 41821 | K53: 41852 | L53: 41883 | M53: 41913 | N53: 41944 | O53: 41974 | P53: 42005 | Q53: 42036 | R53: 42064
G54: 63457 | H54: 55180 | I54: 55180 | J54: 56840 | K54: 56840 | L54: 58829 | M54: 58829 | N54: 62807 | O54: 58829 | P54: 58829 | Q54: 29415 | R54: 63031
E55: 21 | F55: 2015-16 | G55: 42095 | H55: 42125 | I55: 42156 | J55: 42186 | K55: 42217 | L55: 42248 | M55: 42278 | N55: 42309 | O55: 42339 | P55: 42370 | Q55: 42401 | R55: 42430
G56: 64921 | H56: 60535 | I56: 60535 | J56: 62366 | K56: 62366 | L56: 64123 | M56: 67637 | N56: 64123 | O56: 65263 | P56: 65203 | Q56: 65323 | R56: 65323
E57: 22 | F57: 2016-17 | G57: 42461 | H57: 42491 | I57: 42522 | J57: 42552 | K57: 42583 | L57: 42614 | M57: 42644 | N57: 42675 | O57: 42705 | P57: 42736 | Q57: 42767 | R57: 42795
G58: 66240 | H58: 72291 | I58: 67200 | J58: 69060 | K58: 70889 | L58: 73628 | M58: 73688 | N58: 77272 | O58: 83704 | P58: 74866 | Q58: 74866 | R58: 78739
E59: 23 | F59: 2017-18 | G59: 42826 | H59: 42856 | I59: 42887 | J59: 42917 | K59: 42948 | L59: 42979 | M59: 43009 | N59: 43040 | O59: 43070 | P59: 43101 | Q59: 43132 | R59: 43160
G60: 76157 | H60: 76157 | I60: 186250 | J60: 89232 | K60: 89232 | L60: 91806 | M60: 90090 | N60: 90090 | O60: 90090 | P60: 90090 | Q60: 90090 | R60: 95238
E61: 24 | F61: 2018-19 | G61: 43191 | H61: 43221 | I61: 43252 | J61: 43282 | K61: 43313 | L61: 43344 | M61: 43374 | N61: 43405 | O61: 43435 | P61: 43466 | Q61: 43497 | R61: 43525
G62: 91806 | H62: 91806 | I62: 91806 | J62: 94588 | K62: 98124 | L62: 96356 | M62: 96356 | N62: 96356 | O62: 96356 | P62: 96356 | Q62: 96356 | R62: 104312
E63: 25 | F63: 2019-20 | G63: 43556 | H63: 43586 | I63: 43617 | J63: 43647 | K63: 43678 | L63: 43709 | M63: 43739 | N63: 43770 | O63: 43800 | P63: 43831 | Q63: 43862 | R63: 43891
G64: 99008 | H64: 99008 | I64: 99008 | J64: 65047 | K64: 102032 | L64: 114046 | M64: 106587 | N64: 106587 | O64: 106587 | P64: 106587 | Q64: 106587 | R64: 106587
E65: 26 | F65: 2020-21 | G65: 43922 | H65: 43952 | I65: 43983 | J65: 44013 | K65: 44044 | L65: 44075 | M65: 44105 | N65: 44136 | O65: 44166 | P65: 44197 | Q65: 44228 | R65: 44256
G66: 106587 | H66: 106587 | I66: 106587 | J66: 109746 | K66: 109746 | L66: 109746 | M66: 109746 | N66: 109746 | O66: 109746 | P66: 109746 | Q66: 109746 | R66: 109746
E67: 27 | F67: 2021-22 | G67: 44287 | H67: 44317 | I67: 44348 | J67: 44378 | K67: 44409 | L67: 44440 | M67: 44470 | N67: 44501 | O67: 44531 | P67: 44562 | Q67: 44593 | R67: 44621
G68: 109746
E69: 28 | F69: 2022-23 | G69: 44652 | H69: 44682 | I69: 44713 | J69: 44743 | K69: 44774 | L69: 44805 | M69: 44835 | N69: 44866 | O69: 44896 | P69: 44927 | Q69: 44958 | R69: 44986
E71: 29 | F71: 2023-24 | G71: 45017 | H71: 45047 | I71: 45078 | J71: 45108 | K71: 45139 | L71: 45170 | M71: 45200 | N71: 45231 | O71: 45261 | P71: 45292 | Q71: 45323 | R71: 45352

Sheet Pension Cal
A1: EPS 1995 Pension - "Ceiling Amount" & "Actual Salary" Pension Calculation
A2: Developed by Mr. Neeraj Bhargava (9950826109) in consultation with Mr. Parveen Kohli (9810306699) & with technical support from Mr. C Ramasamy
A4: Please read Instructions given in INSTRUCTIONS sheet carefully
A6: Name | C6: =Input!K8 -> VARRINDER KAUR RAINA | I6: Year | K6: Month | L6: Days | N6: Computation of Past Service Factor
A7: Date of Birth | I7: =YEAR(Input!I8) -> 1961 | K7: =MONTH(Input!I8) -> 4 | L7: =DAY(Input!I8) -> 15 | N7: Years of Past Service | V7: Salary <2500 | Y7: Salary >=2500
A8: Date of Joining PF | I8: =YEAR(Input!I9) -> 1980 | K8: =MONTH(Input!I9) -> 1 | L8: =DAY(Input!I9) -> 1 | N8: <= 11 Years | V8: 80 | Y8: 85
A9: Date of EPS Joining | F9: 35019 | I9: =YEAR(F9) -> 1995 | K9: =MONTH('Pension Cal'!F9) -> 11 | L9: =DAY('Pension Cal'!F9) -> 16 | N9: >11 Years & <=15 years | V9: 95 | Y9: 105
A10: Date of Change in Table B | F10: 39609 | I10: =YEAR(F10) -> 2008 | K10: =MONTH(F10) -> 6 | L10: =DAY(F10) -> 10 | N10: > 15 Years <= 20 years | V10: 120 | Y10: 135
A11: Date of Ceiling Change | F11: 41883 | I11: =YEAR(F11) -> 2014 | K11: =MONTH('Pension Cal'!F11) -> 9 | L11: =DAY('Pension Cal'!F11) -> 1 | N11: >20 years | V11: 150 | Y11: 170
A12: Date of Superannuation | F12: =DATE(I12,K12,L12) -> 43570 | I12: =I7+58 -> 2019 | K12: =K7 -> 4 | L12: =L7 -> 15 | N12: DERIVED VALUE FOR THE PAST SERVICE | V12: =IF(Q24=0,0,VLOOKUP(Q24,D58:E86,2,1)) -> 120 | Y12: =IF(Q24=0,0,VLOOKUP(Q24,D58:G86,4,1)) -> 135
A13: Date of Commencement of Ceiling Amount Pension | I13: =YEAR(Input!I11) -> 2019 | K13: =MONTH(Input!I11) -> 5 | L13: =DAY(Input!I11) -> 1 | N13: Past Service Factor (PSF) | Y13: =IF(Input!L10<=2500,V12,Y12) -> 135
A14: Date of Commencement of Actual Salary Pension | I14: =YEAR(Input!O11) -> 2019 | K14: =MONTH(Input!O11) -> 5 | L14: =DAY(Input!O11) -> 1
A16: Additional Details: | E16: Ceiling upto 31.08.2014 | I16: Ceiling from 01.09.2014 | N16: Computation of Table B Factor (GSR 134E / GSR 438E)
N17: Service years from 16-11-1995 to Date of Exit | V17: DOE<10.06.2008 | Y17: DOE>=10.06.2008
A18: On Ceiling pension | E18: 6500 | I18: 15000 | N18: Less than | Q18: =M27/360 -> 23.458333 | S18: Years | V18: =IF(M24=0,0,VLOOKUP(Q18,Y58:Z92,2,1)) -> 9.39 | Y18: =IF(M24=0,0,VLOOKUP(Q18,N58:Q92,4,1)) -> 6.101
A19: On Actual pension | E19: No cap | I19: No cap | N19: Table B Value | Y19: =IF(Input!I10<=F10,V18,Y18) -> 6.101
A21: EPS Para Ref. | E21: Details | M21: No. of days | Q21: Years | T21: Months | W21: Days
A22: 9. Eligible Service | E22: Total Service | M22: =DAYS360(Input!I9,Input!I10) -> 14160 | Q22: =INT(M22/360) -> 39 | T22: =INT((M22/360-Q22)*12) -> 4 | W22: =M22-Q22*360-T22*30 -> 0
E23: Eligible Service | Q23: =IF(2*(M22/360)>(2*Q22+1),(Q22+1),(M22/360)) -> 39.333333 | T23: 0 | W23: 0
E24: Past Service (service upto 15.11.1995) | M24: =IF(Input!I9=0,0,IF(Input!I9>=F9,0,DAYS360(Input!I9,F9))) -> 5715 | Q24: =INT(M24/360) -> 15 | T24: =INT((M24/360-Q24)*12) -> 10 | W24: =M24-Q24*360-T24*30 -> 15
A25: 10 (1) Pensionable Service | E25: Service from 16-11-1995 to 31-08-2014 or DoE | M25: =IF(Input!I9=0,0,IF(Input!I9>=F9,DAYS360(Input!I9,F11),IF(Input!I10<='Pension Cal'!F11,DAYS360('Pension Cal'!F9,Input!I10),DAYS360('Pension Cal'!F9,'Pension Cal'!F11)))) -> 6765 | Q25: =INT(M25/360) -> 18 | T25: =INT((M25/360-Q25)*12) -> 9 | W25: =(M25-Q25*360-T25*30) -> 15
E26: Service from 01-09-2014 to Date of Exit | M26: =IF(Input!I11<='Pension Cal'!F11,0,DAYS360('Pension Cal'!F11,Input!I11)) -> 1680 | Q26: =INT(M26/360) -> 4 | T26: =INT((M26/360-Q26)*12) -> 8 | W26: =(M26-Q26*360-T26*30) -> 0
E27: Contribution received for the period | M27: =SUM(M25:M26) -> 8445 | Q27: =INT(M27/360) -> 23 | T27: =INT((M27/360-Q27)*12) -> 5 | W27: =M27-Q27*360-T27*30 -> 15
A28: 10 (2) Weightage of 2 years | E28: Weightage Service | M28: =IF(Input!N10=2,720,0) -> 0 | Q28: =INT(M28/360) -> 0 | T28: =INT((M28/360-Q28)*12) -> 0 | W28: =M28-Q28*360-T28*30 -> 0
E29: Non contributory period | M29: =Input!N9 -> 0 | Q29: =INT(M29/360) -> 0 | T29: =INT((M29/360-Q29)*12) -> 0 | W29: =M29-Q29*360-T29*30 -> 0
E30: Total Pensionable Service considering 6,500 limit | M30: =M25+M28-M29 -> 6765 | Q30: =Q25+Q28-Q29 -> 18 | T30: =T25+T28-T29 -> 9 | W30: =W25+W28-W29 -> 15
E31: Total Pensionable Service considering 15,000 limit | M31: =M27+M28-M29 -> 8445 | Q31: =Q27+Q28-Q29 -> 23 | T31: =T27+T28-T29 -> 5 | W31: =W27+W28-W29 -> 15
A32: Early Exit Cal. | E32: Diff in Superannuation & exit dates | M32: =IF(Input!I11=0,0,ABS(DAYS360(F12,Input!I11))) -> 16 | Q32: =INT(M32/360) -> 0 | T32: =INT((M32/360-Q32)*12) -> 0 | W32: =M32-Q32*360-T32*30 -> 16
M34: Ceiling Salary Pension | V34: Actual Salary Pension
A35: 11. Pensionable Salary etc. | H35: Pensionable Service (Days) | M35: Pensionable Salary | O35: Past Service Factor | R35: Table B | V35: Pensionable Salary | X35: Past Service Factor | AA35: Table B
V36: Pre 01-09-2014 retirees | W36: Post 01-09-2014 retirees
A37: For Normal / Higher Pension | H37: =M30 -> 6765 | M37: =IF(Input!I10=0,0,IF(Input!I10<=F11,E18,((Q26*12+T26+W26/30)*I18+(60-(Q26*12+T26+W26/30))*E18)/((5*360)/30))) -> 14433.333 | O37: =Y13 -> 135 | R37: =Y19 -> 6.101 | V37: =IF(Input!I10>'Pension Cal'!F11,0,AVERAGE(('Amount Cal'!G202:'Amount Cal'!R202))) -> 0 | W37: =IF(Input!I10<='Pension Cal'!F11,0,AVERAGE(('Amount Cal'!G202:'Amount Cal'!R202),('Amount Cal'!G204:'Amount Cal'!R204),('Amount Cal'!G206:'Amount Cal'!R206),('Amount Cal'!G208:'Amount Cal'!R208),('Amount Cal'!G210:'Amount Cal'!R210))) -> 86909.967 | X37: =Y13 -> 135 | AA37: =Y19 -> 6.101
E39: Break up Details | M39: Pension Calculations
M40: Ceiling Salary Pension | R40: Actual Salary Pension
A42: 12 (1) (a) Monthly Pension | E42: For Actual Service @ 6,500/- | M42: =IF('Amount Cal'!G202=0,0,IF('Amount Cal'!G202<=E18,(M31/360)*(E18/70),(M30/360)*(E18/70))) -> 1744.9405 | R42: =IF(Input!I10<'Pension Cal'!F11,(V37/70)*(H37/360),(W37/70)*(H37/360)) -> 23331.187
E43: For Actual Service @ 15,000/- | M43: =IF('Amount Cal'!G202=0,0,IF('Amount Cal'!G202>E18,M37/70*M26/360,0)) -> 962.22222
E44: For Past Service (Table A x Table B) | M44: =IF('Amount Cal'!G202=0,0,IF(Input!I9=0,0,O37*R37)) -> 823.635 | R44: =IF('Amount Cal'!G202=0,0,X37*AA37) -> 823.635
E45: Total | M45: =M42+M43+M44 -> 3530.7977 | R45: =R42+R44 -> 24154.822
E46: Superannuation Pension | M46: =ROUND(M45,0) -> 3531 | R46: =ROUND(R45,0) -> 24155
E47: Spouse Pension (after Death) | M47: =M46/2 -> 1765.5 | R47: =R46/2 -> 12077.5
E48: Children Pension (upto 25 yrs of Age) | M48: =ROUND(M47/4,0) -> 441 | R48: =ROUND(R47/4,0) -> 3019
E49: Orphan Pension | M49: =ROUND(M47*3/4,0) -> 1324 | R49: =ROUND(R47*3/4,0) -> 9058
A51: 12 (7) | E51: Reduced Monthly Pension | M51: =IF(Q32<=0,0,IF(Q32=1,M46*(1-4/100),IF(Q32=2,M46*(1-8.16/100),IF(Q32=3,M46*(1-12.49/100),IF(Q32=4,M46*(1-16.99/100),IF(Q32=5,M46*(1-21.67/100),M46*(1-25/100))))))) -> 0 | R51: =IF(Q32<=0,0,IF(Q32=1,R46*(1-4/100),IF(Q32=2,R46*(1-8.16/100),IF(Q32=3,R46*(1-12.49/100),IF(Q32=4,R46*(1-16.99/100),IF(Q32=5,R46*(1-21.67/100),R46*(1-25/100))))))) -> 0
A52: 12 (7B) a (i) | E52: Enhanced Monthly Pension | M52: =IF(Q32<=0,0,IF(Q32=1,M46*(1+4/100),M46*(1+8.16/100))) -> 0 | R52: =IF(Q32<=0,0,IF(Q32=1,R46*(1+4/100),R46*(1+8.16/100))) -> 0
B54: VLOOKUP Past Service | K54: VLOOKUP REF. TABLE B "CURRENT" | V54: VLOOKUP REF. TABLE B "OLD"
K55: GSR 438E WEF 10.06.2008 | V55: GSR 134E DT 16.03.1996
B56: SALARY FACTOR | K56: Table B Effective > = 10-06-2008 | V56: Table B Effective upto 09-06-2008
B57: YEARS | D57: .T. | E57: <2500 | G57: >2500 | K57: PENSIONABLE SERVICE | V57: PENSIONABLE SERVICE
B58: 1 | D58: 0 | E58: 80 | G58: 85 | K58: YEARS | N58: TRUE/NOT | Q58: VALUE | V58: YEARS | Y58: TRUE/NOT | Z58: VALUE
B59: 2 | D59: 1 | E59: 80 | G59: 85 | K59: Less than 1 | N59: 0 | Q59: 1.039 | V59: Less than 1 | Y59: 0 | Z59: 1.049
B60: 3 | D60: 2 | E60: 80 | G60: 85 | K60: Less than 2 | N60: 1 | Q60: 1.122 | V60: Less than 2 | Y60: 1 | Z60: 1.154
B61: 4 | D61: 3 | E61: 80 | G61: 85 | K61: Less than 3 | N61: 2 | Q61: 1.212 | V61: Less than 3 | Y61: 2 | Z61: 1.269
B62: 5 | D62: 4 | E62: 80 | G62: 85 | K62: Less than 4 | N62: 3 | Q62: 1.309 | V62: Less than 4 | Y62: 3 | Z62: 1.396
B63: 6 | D63: 5 | E63: 80 | G63: 85 | K63: Less than 5 | N63: 4 | Q63: 1.413 | V63: Less than 5 | Y63: 4 | Z63: 1.536
B64: 7 | D64: 6 | E64: 80 | G64: 85 | K64: Less than 6 | N64: 5 | Q64: 1.526 | V64: Less than 6 | Y64: 5 | Z64: 1.689
B65: 8 | D65: 7 | E65: 80 | G65: 85 | K65: Less than 7 | N65: 6 | Q65: 1.649 | V65: Less than 7 | Y65: 6 | Z65: 1.858
B66: 9 | D66: 8 | E66: 80 | G66: 85 | K66: Less than 8 | N66: 7 | Q66: 1.781 | V66: Less than 8 | Y66: 7 | Z66: 2.044
B67: 10 | D67: 9 | E67: 80 | G67: 85 | K67: Less than 9 | N67: 8 | Q67: 1.923 | V67: Less than 9 | Y67: 8 | Z67: 2.248
B68: 11 | D68: 10 | E68: 80 | G68: 85 | K68: Less than 10 | N68: 9 | Q68: 2.077 | V68: Less than 10 | Y68: 9 | Z68: 2.473
B69: 12 | D69: 11 | E69: 95 | G69: 105 | K69: Less than 11 | N69: 10 | Q69: 2.243 | V69: Less than 11 | Y69: 10 | Z69: 2.72
B70: 13 | D70: 12 | E70: 95 | G70: 105 | K70: Less than 12 | N70: 11 | Q70: 2.423 | V70: Less than 12 | Y70: 11 | Z70: 2.992
... B82: 25 | D82: 24 | E82: 150 | G82: 170 | K82: Less than 24 | N82: 23 | Q82: 6.101 | V82: Less than 24 | Y82: 23 | Z82: 9.39
B83: 26 | D83: 25 | E83: 150 | G83: 170 | K83: Less than 25 | N83: 24 | Q83: 6.589
B84: 27 | D84: 26 | E84: 150 | G84: 170 | K84: Less than 26 | N84: 25 | Q84: 7.117
B85: 28 | D85: 27 | E85: 150 | G85: 170 | K85: Less than 27 | N85: 26 | Q85: 7.686
B86: 29 | D86: 28 | E86: 150 | G86: 170 | K86: Less than 28 | N86: 27 | Q86: 8.301
K87: Less than 29 | N87: 28 | Q87: 8.965
K88: Less than 30 | N88: 29 | Q88: 9.682
K89: Less than 31 | N89: 30 | Q89: 10.457
K90: Less than 32 | N90: 31 | Q90: 11.294
K91: Less than 33 | N91: 32 | Q91: 12.197
K92: Less than 34 | N92: 33 | Q92: 13.173

Sheet Amount Cal
A1: Month | B1: Salary | D1: EPS 1995 Pension - Differential Amount and Interest Payable Calculations
A2: 34790 | D2: Developed by Mr. Neeraj Bhargava (9950826109) in consultation with Mr. Parveen Kohli (9810306699) & with technical support from Mr. C Ramasamy
A3: 34820
A4: 34851 | D4: Please read Instructions given in INSTRUCTIONS sheet carefully
A5: 34881
A6: 34912 | D6: Name | G6: Wage Ceiling | H6: From | I6: To | J6: Ceiling | K6: Max Contribution | M6: Wage Ceiling | N6: From | O6: To | P6: Ceiling | Q6: Max Contribution | S6: Wage Ceiling | T6: From | U6: Ceiling | V6: Max Contribution
A7: 34943 | D7: =Input!K8 -> VARRINDER KAUR RAINA | G7: Ceiling 1 | H7: 34344 | I7: 31-05-2001 | J7: 5000 | K7: 417 | M7: Ceiling 2 | N7: 37043 | O7: 31-08-2014 | P7: 6500 | Q7: 541 | S7: Ceiling 3 | T7: 41883 | U7: 15000 | V7: 1250
A8: 34973
A9: 35004 | D9: Date of Exit | J9: Date of commencement of "Ceiling Amount Pension" | Q9: Date of commencement of "Actual Salary Pension"
A10: 35034 | B10: =Input!O16 -> 0 | D10: Year | E10: Month | F10: Days | J10: Year | K10: Month | L10: Days | Q10: Year | R10: Month | S10: Days
A11: 35065 | B11: =Input!P16 -> 0 | D11: =IF(Input!I10=0,0,YEAR(Input!I10)) -> 2019 | E11: =IF(Input!I10=0,0,MONTH(Input!I10)) -> 5 | F11: =IF(Input!I10=0,0,DAY(Input!I10)) -> 1 | G11: =IF(Input!I10=0,1,DATE(D11,E11,1)) -> 43586 | H11: =E11+1 -> 6 | I11: =IF(Input!I10=0,1,DATE(D11,H11,1)) -> 43617 | J11: =IF(Input!I11=0,0,YEAR(Input!I11)) -> 2019 | K11: =IF(Input!I11=0,0,MONTH(Input!I11)) -> 5 | L11: =IF(Input!I11=0,0,DAY(Input!I11)) -> 1 | M11: =IF(Input!I11=0,1,DATE(J11,K11,1)) -> 43586 | N11: =K11+1 -> 6 | O11: =IF(Input!I11=0,1,DATE(J11,N11,1)) -> 43617 | Q11: =IF(Input!O11=0,0,YEAR(Input!O11)) -> 2019 | R11: =IF(Input!O11=0,0,MONTH(Input!O11)) -> 5 | S11: =IF(Input!O11=0,0,DAY(Input!O11)) -> 1 | T11: =IF(Input!O11=0,1,DATE(Q11,R11,1)) -> 43586 | U11: =R11-1 -> 4 | V11: =IF(Input!O11=0,1,DATE(Q11,U11,1)) -> 43556
A12: 35096 | B12: =Input!Q16 -> 0
A13: 35125 | B13: =Input!R16 -> 0 | D13: S No | E13: Financial Year & Rate of Interest | F13: Month | G13: April | H13: May | I13: June | J13: July | K13: August | L13: September | M13: October | N13: November | O13: December | P13: January | Q13: February | R13: March | S13: Total | T13: Differential Amount to be paid
A14: 35156 | B14: =Input!G$18 -> 0 | T14: Contribution | U14: Interest | V14: Total
A15: 35186 | B15: =Input!H$18 -> 0 | D15: 1 | E15: 1995-96 | F15: PF'able Salary | O15: 35034 | P15: 35065 | Q15: 35096 | R15: 35125 | S15: =SUM(Input!O16:R16) -> 0
A16: 35217 | B16: =Input!I$18 -> 0 | F16: 8.33% of PF'able Salary | O16: =IF(Input!O16=0,0,INT((Input!O16*8.33/100)+0.5)) -> 0 | P16: =IF(Input!P16=0,0,INT((Input!P16*8.33/100)+0.5)) -> 0 | Q16: =IF(Input!Q16=0,0,INT((Input!Q16*8.33/100)+0.5)) -> 0 | R16: =IF(Input!R16=0,0,INT((Input!R16*8.33/100)+0.5)) -> 0 | S16: =SUM(O16:R16) -> 0
A17: 35247 | B17: =Input!J$18 -> 0 | F17: Pension contribution (on ceiling) | O17: =IF(2*Input!O16<=$J$7,INT((Input!O16*8.33%)+0.5),INT(($J$7*8.33%)/2+0.5)) -> 0 | P17: =IF(Input!P16<=$J$7,INT((Input!P16*8.33%)+0.5),INT(($J$7*8.33%)+0.5)) -> 0 | Q17: =IF(Input!Q16<=$J$7,INT((Input!Q16*8.33%)+0.5),INT(($J$7*8.33%)+0.5)) -> 0 | R17: =IF(Input!R16<=$J$7,INT((Input!R16*8.33%)+0.5),INT(($J$7*8.33%)+0.5)) -> 0 | S17: =SUM(O17:R17) -> 0
A18: 35278 | B18: =Input!K$18 -> 0 | F18: Addl Amount Payable on PF'able Salary | O18: =IF(O16-O17<=0,0,O16-O17) -> 0 | P18: =IF(P16-P17<=0,0,P16-P17) -> 0 | Q18: =IF(Q16-Q17<=0,0,Q16-Q17) -> 0 | R18: =IF(R16-R17<=0,0,R16-R17) -> 0 | S18: =SUM(O18:R18) -> 0
A19: 35309 | B19: =Input!L$18 -> 0 | E19: Interest rate | F19: Progressive balance | O19: =IF(O15=0,0,IF($T$11<=Input!O14,0,N18+N19)) -> 0 | P19: =IF(P15=0,0,IF($T$11<=Input!P15,0,O18+O19)) -> 0 | Q19: =IF(Q15=0,0,IF($T$11<=Input!Q15,0,P18+P19)) -> 0 | R19: =IF(R15=0,0,IF($T$11<=Input!R15,0,Q18+Q19)) -> 0 | T19: =SUM(O18:R18) -> 0 | U19: =SUM(P20:R20) -> 0 | V19: =SUM(T19,U19) -> 0
A20: 35339 | B20: =Input!M$18 -> 0 | E20: 0.12 | F20: Interest amount | O20: =O19/12*$E20 -> 0 | P20: =P19/12*$E20 -> 0 | Q20: =Q19/12*$E20 -> 0 | R20: =R19/12*$E20 -> 0 | S20: =SUM(O20:R20) -> 0 | T20: =SUM(T19) -> 0 | U20: =SUM(U19) -> 0 | V20: =SUM(V19) -> 0
A21: 35370 | B21: =Input!N$18 -> 0 | D21: 2 | E21: 1996-97 | F21: PF'able Salary | G21: 35156 | H21: 35186 | I21: 35217 | J21: 35247 | K21: 35278 | L21: 35309 | M21: 35339 | N21: 35370 | O21: 35400 | P21: 35431 | Q21: 35462 | R21: 35490 | S21: =SUM(Input!G18:R18) -> 0
A22: 35400 | B22: =Input!O$18 -> 0 | F22: 8.33% of PF'able Salary | G22: =IF(Input!G18=0,0,INT((Input!G18*8.33/100)+0.5)) -> 0 | H22: =IF(Input!H18=0,0,INT((Input!H18*8.33/100)+0.5)) -> 0 | I22: =IF(Input!I18=0,0,INT((Input!I18*8.33/100)+0.5)) -> 0 | J22: =IF(Input!J18=0,0,INT((Input!J18*8.33/100)+0.5)) -> 0 | K22: =IF(Input!K18=0,0,INT((Input!K18*8.33/100)+0.5)) -> 0 | L22: =IF(Input!L18=0,0,INT((Input!L18*8.33/100)+0.5)) -> 0 | M22: =IF(Input!M18=0,0,INT((Input!M18*8.33/100)+0.5)) -> 0 | N22: =IF(Input!N18=0,0,INT((Input!N18*8.33/100)+0.5)) -> 0 | ... R22: =IF(Input!R18=0,0,INT((Input!R18*8.33/100)+0.5)) -> 0 | S22: =SUM(G22:R22) -> 0
A23: 35431 | B23: =Input!P$18 -> 0 | F23: Pension contribution (on ceiling) | G23: =IF(Input!G18<=$J$7,INT((Input!G18*8.33%)+0.5),INT(($J$7*8.33%)+0.5)) -> 0 | H23: =IF(Input!H18<=$J$7,INT((Input!H18*8.33%)+0.5),INT(($J$7*8.33%)+0.5)) -> 0 | I23: =IF(Input!I18<=$J$7,INT((Input!I18*8.33%)+0.5),INT(($J$7*8.33%)+0.5)) -> 0 | J23: =IF(Input!J18<=$J$7,INT((Input!J18*8.33%)+0.5),INT(($J$7*8.33%)+0.5)) -> 0 | K23: =IF(Input!K18<=$J$7,INT((Input!K18*8.33%)+0.5),INT(($J$7*8.33%)+0.5)) -> 0 | L23: =IF(Input!L18<=$J$7,INT((Input!L18*8.33%)+0.5),INT(($J$7*8.33%)+0.5)) -> 0 | M23: =IF(Input!M18<=$J$7,INT((Input!M18*8.33%)+0.5),INT(($J$7*8.33%)+0.5)) -> 0 | N23: =IF(Input!N18<=$J$7,INT((Input!N18*8.33%)+0.5),INT(($J$7*8.33%)+0.5)) -> 0 | ... R23: =IF(Input!R18<=$J$7,INT((Input!R18*8.33%)+0.5),INT(($J$7*8.33%)+0.5)) -> 0 | S23: =SUM(G23:R23) -> 0
A24: 35462 | B24: =Input!Q$18 -> 0 | F24: Addl Amount Payable on PF'able Salary | G24: =IF(G22-G23<=0,0,G22-G23) -> 0 | H24: =IF(H22-H23<=0,0,H22-H23) -> 0 | I24: =IF(I22-I23<=0,0,I22-I23) -> 0 | J24: =IF(J22-J23<=0,0,J22-J23) -> 0 | K24: =IF(K22-K23<=0,0,K22-K23) -> 0 | L24: =IF(L22-L23<=0,0,L22-L23) -> 0 | M24: =IF(M22-M23<=0,0,M22-M23) -> 0 | N24: =IF(N22-N23<=0,0,N22-N23) -> 0 | ... R24: =IF(R22-R23<=0,0,R22-R23) -> 0 | S24: =SUM(G24:R24) -> 0
A25: 35490 | B25: =Input!R$18 -> 0 | E25: Interest rate | F25: Progressive balance | G25: =IF(G21=0,0,IF($T$11<=Input!G17,0,R18+R19+U19)) -> 0 | H25: =IF(H21=0,0,IF($T$11<=Input!H17,0,G24+G25)) -> 0 | I25: =IF(I21=0,0,IF($T$11<=Input!I17,0,H24+H25)) -> 0 | J25: =IF(J21=0,0,IF($T$11<=Input!J17,0,I24+I25)) -> 0 | K25: =IF(K21=0,0,IF($T$11<=Input!K17,0,J24+J25)) -> 0 | L25: =IF(L21=0,0,IF($T$11<=Input!L17,0,K24+K25)) -> 0 | M25: =IF(M21=0,0,IF($T$11<=Input!M17,0,L24+L25)) -> 0 | N25: =IF(N21=0,0,IF($T$11<=Input!N17,0,M24+M25)) -> 0 | O25: =IF(O21=0,0,IF($T$11<=Input!O17,0,N24+N25)) -> 0 | ... R25: =IF(R21=0,0,IF($T$11<=Input!R17,0,Q24+Q25)) -> 0 | T25: =SUM(G24:R24) -> 0 | U25: =SUM(G26:R26) -> 0 | V25: =SUM(T25,U25) -> 0
A26: 35521 | B26: =Input!G$20 -> 0 | E26: 0.12 | F26: Interest amount | G26: =G25/12*$E26 -> 0 | H26: =H25/12*$E26 -> 0 | I26: =I25/12*$E26 -> 0 | J26: =J25/12*$E26 -> 0 | K26: =K25/12*$E26 -> 0 | L26: =L25/12*$E26 -> 0 | M26: =M25/12*$E26 -> 0 | N26: =N25/12*$E26 -> 0 | ... R26: =R25/12*$E26 -> 0 | S26: =SUM(G26:R26) -> 0 | T26: =SUM(T19,T25) -> 0 | U26: =SUM(U19,U25) -> 0 | V26: =SUM(V19,V25) -> 0
A27: 35551 | B27: =Input!H$20 -> 0 | D27: 3 | E27: 1997-98 | F27: PF'able Salary | G27: 35521 | H27: 35551 | I27: 35582 | J27: 35612 | K27: 35643 | L27: 35674 | M27: 35704 | N27: 35735 | O27: 35765 | P27: 35796 | Q27: 35827 | R27: 35855 | S27: =SUM(Input!G20:R20) -> 0
A28: 35582 | B28: =Input!I$20 -> 0 | F28: 8.33% of PF'able Salary | G28: =IF(Input!G20=0,0,INT((Input!G20*8.33/100)+0.5)) -> 0 | H28: =IF(Input!H20=0,0,INT((Input!H20*8.33/100)+0.5)) -> 0 | I28: =IF(Input!I20=0,0,INT((Input!I20*8.33/100)+0.5)) -> 0 | J28: =IF(Input!J20=0,0,INT((Input!J20*8.33/100)+0.5)) -> 0 | K28: =IF(Input!K20=0,0,INT((Input!K20*8.33/100)+0.5)) -> 0 | L28: =IF(Input!L20=0,0,INT((Input!L20*8.33/100)+0.5)) -> 0 | M28: =IF(Input!M20=0,0,INT((Input!M20*8.33/100)+0.5)) -> 0 | N28: =IF(Input!N20=0,0,INT((Input!N20*8.33/100)+0.5)) -> 0 | ... R28: =IF(Input!R20=0,0,INT((Input!R20*8.33/100)+0.5)) -> 0 | S28: =SUM(G28:R28) -> 0
A29: 35612 | B29: =Input!J$20 -> 0 | F29: Pension contribution (on ceiling) | G29: =IF(Input!G20<=$J$7,INT((Input!G20*8.33%)+0.5),INT(($J$7*8.33%)+0.5)) -> 0 | H29: =IF(Input!H20<=$J$7,INT((Input!H20*8.33%)+0.5),INT(($J$7*8.33%)+0.5)) -> 0 | I29: =IF(Input!I20<=$J$7,INT((Input!I20*8.33%)+0.5),INT(($J$7*8.33%)+0.5)) -> 0 | J29: =IF(Input!J20<=$J$7,INT((Input!J20*8.33%)+0.5),INT(($J$7*8.33%)+0.5)) -> 0 | K29: =IF(Input!K20<=$J$7,INT((Input!K20*8.33%)+0.5),INT(($J$7*8.33%)+0.5)) -> 0 | L29: =IF(Input!L20<=$J$7,INT((Input!L20*8.33%)+0.5),INT(($J$7*8.33%)+0.5)) -> 0 | M29: =IF(Input!M20<=$J$7,INT((Input!M20*8.33%)+0.5),INT(($J$7*8.33%)+0.5)) -> 0 | N29: =IF(Input!N20<=$J$7,INT((Input!N20*8.33%)+0.5),INT(($J$7*8.33%)+0.5)) -> 0 | ... R29: =IF(Input!R20<=$J$7,INT((Input!R20*8.33%)+0.5),INT(($J$7*8.33%)+0.5)) -> 0 | S29: =SUM(G29:R29) -> 0
A30: 35643 | B30: =Input!K$20 -> 0 | F30: Addl Amount Payable on PF'able Salary | G30: =IF(G28-G29<=0,0,G28-G29) -> 0 | H30: =IF(H28-H29<=0,0,H28-H29) -> 0 | I30: =IF(I28-I29<=0,0,I28-I29) -> 0 | J30: =IF(J28-J29<=0,0,J28-J29) -> 0 | K30: =IF(K28-K29<=0,0,K28-K29) -> 0 | L30: =IF(L28-L29<=0,0,L28-L29) -> 0 | M30: =IF(M28-M29<=0,0,M28-M29) -> 0 | N30: =IF(N28-N29<=0,0,N28-N29) -> 0 | ... R30: =IF(R28-R29<=0,0,R28-R29) -> 0 | S30: =SUM(G30:R30) -> 0
A31: 35674 | B31: =Input!L$20 -> 0 | E31: Interest rate | F31: Progressive balance | G31: =IF(G27=0,0,IF($T$11<=Input!G19,0,R24+R25+U25)) -> 0 | H31: =IF(H27=0,0,IF($T$11<=Input!H19,0,G30+G31)) -> 0 | I31: =IF(I27=0,0,IF($T$11<=Input!I19,0,H30+H31)) -> 0 | J31: =IF(J27=0,0,IF($T$11<=Input!J19,0,I30+I31)) -> 0 | K31: =IF(K27=0,0,IF($T$11<=Input!K19,0,J30+J31)) -> 0 | L31: =IF(L27=0,0,IF($T$11<=Input!L19,0,K30+K31)) -> 0 | M31: =IF(M27=0,0,IF($T$11<=Input!M19,0,L30+L31)) -> 0 | N31: =IF(N27=0,0,IF($T$11<=Input!N19,0,M30+M31)) -> 0 | O31: =IF(O27=0,0,IF($T$11<=Input!O19,0,N30+N31)) -> 0 | ... R31: =IF(R27=0,0,IF($T$11<=Input!R19,0,Q30+Q31)) -> 0 | T31: =SUM(G30:R30) -> 0 | U31: =SUM(G32:R32) -> 0 | V31: =SUM(T31,U31) -> 0
A32: 35704 | B32: =Input!M$20 -> 0 | E32: 0.12 | F32: Interest amount | G32: =G31/12*$E32 -> 0 | H32: =H31/12*$E32 -> 0 | I32: =I31/12*$E32 -> 0 | J32: =J31/12*$E32 -> 0 | K32: =K31/12*$E32 -> 0 | L32: =L31/12*$E32 -> 0 | M32: =M31/12*$E32 -> 0 | N32: =N31/12*$E32 -> 0 | ... R32: =R31/12*$E32 -> 0 | S32: =SUM(G32:R32) -> 0 | T32: =SUM(T19,T25,T31) -> 0 | U32: =SUM(U19,U25,U31) -> 0 | V32: =SUM(V19,V25,V31) -> 0
A33: 35735 | B33: =Input!N$20 -> 0 | D33: 4 | E33: 1998-99 | F33: PF'able Salary | G33: 35886 | H33: 35916 | I33: 35947 | J33: 35977 | K33: 36008 | L33: 36039 | M33: 36069 | N33: 36100 | O33: 36130 | P33: 36161 | Q33: 36192 | R33: 36220 | S33: =SUM(Input!G22:R22) -> 0
A34: 35765 | B34: =Input!O$20 -> 0 | F34: 8.33% of PF'able Salary | G34: =IF(Input!G22=0,0,INT((Input!G22*8.33/100)+0.5)) -> 0 | H34: =IF(Input!H22=0,0,INT((Input!H22*8.33/100)+0.5)) -> 0 | I34: =IF(Input!I22=0,0,INT((Input!I22*8.33/100)+0.5)) -> 0 | J34: =IF(Input!J22=0,0,INT((Input!J22*8.33/100)+0.5)) -> 0 | K34: =IF(Input!K22=0,0,INT((Input!K22*8.33/100)+0.5)) -> 0 | L34: =IF(Input!L22=0,0,INT((Input!L22*8.33/100)+0.5)) -> 0 | M34: =IF(Input!M22=0,0,INT((Input!M22*8.33/100)+0.5)) -> 0 | N34: =IF(Input!N22=0,0,INT((Input!N22*8.33/100)+0.5)) -> 0 | ... R34: =IF(Input!R22=0,0,INT((Input!R22*8.33/100)+0.5)) -> 0 | S34: =SUM(G34:R34) -> 0
A35: 35796 | B35: =Input!P$20 -> 0 | F35: Pension contribution (on ceiling) | G35: =IF(Input!G22<=$J$7,INT((Input!G22*8.33%)+0.5),INT(($J$7*8.33%)+0.5)) -> 0 | H35: =IF(Input!H22<=$J$7,INT((Input!H22*8.33%)+0.5),INT(($J$7*8.33%)+0.5)) -> 0 | I35: =IF(Input!I22<=$J$7,INT((Input!I22*8.33%)+0.5),INT(($J$7*8.33%)+0.5)) -> 0 | J35: =IF(Input!J22<=$J$7,INT((Input!J22*8.33%)+0.5),INT(($J$7*8.33%)+0.5)) -> 0 | K35: =IF(Input!K22<=$J$7,INT((Input!K22*8.33%)+0.5),INT(($J$7*8.33%)+0.5)) -> 0 | L35: =IF(Input!L22<=$J$7,INT((Input!L22*8.33%)+0.5),INT(($J$7*8.33%)+0.5)) -> 0 | M35: =IF(Input!M22<=$J$7,INT((Input!M22*8.33%)+0.5),INT(($J$7*8.33%)+0.5)) -> 0 | N35: =IF(Input!N22<=$J$7,INT((Input!N22*8.33%)+0.5),INT(($J$7*8.33%)+0.5)) -> 0 | ... R35: =IF(Input!R22<=$J$7,INT((Input!R22*8.33%)+0.5),INT(($J$7*8.33%)+0.5)) -> 0 | S35: =SUM(G35:R35) -> 0
A36: 35827 | B36: =Input!Q$20 -> 0 | F36: Addl Amount Payable on PF'able Salary | G36: =IF(G34-G35<=0,0,G34-G35) -> 0 | H36: =IF(H34-H35<=0,0,H34-H35) -> 0 | I36: =IF(I34-I35<=0,0,I34-I35) -> 0 | J36: =IF(J34-J35<=0,0,J34-J35) -> 0 | K36: =IF(K34-K35<=0,0,K34-K35) -> 0 | L36: =IF(L34-L35<=0,0,L34-L35) -> 0 | M36: =IF(M34-M35<=0,0,M34-M35) -> 0 | N36: =IF(N34-N35<=0,0,N34-N35) -> 0 | ... R36: =IF(R34-R35<=0,0,R34-R35) -> 0 | S36: =SUM(G36:R36) -> 0
A37: 35855 | B37: =Input!R$20 -> 0 | E37: Interest rate | F37: Progressive balance | G37: =IF(G33=0,0,IF($T$11<=Input!G21,0,R30+R31+U31)) -> 0 | H37: =IF(H33=0,0,IF($T$11<=Input!H21,0,G36+G37)) -> 0 | I37: =IF(I33=0,0,IF($T$11<=Input!I21,0,H36+H37)) -> 0 | J37: =IF(J33=0,0,IF($T$11<=Input!J21,0,I36+I37)) -> 0 | K37: =IF(K33=0,0,IF($T$11<=Input!K21,0,J36+J37)) -> 0 | L37: =IF(L33=0,0,IF($T$11<=Input!L21,0,K36+K37)) -> 0 | M37: =IF(M33=0,0,IF($T$11<=Input!M21,0,L36+L37)) -> 0 | N37: =IF(N33=0,0,IF($T$11<=Input!N21,0,M36+M37)) -> 0 | O37: =IF(O33=0,0,IF($T$11<=Input!O21,0,N36+N37)) -> 0 | ... R37: =IF(R33=0,0,IF($T$11<=Input!R21,0,Q36+Q37)) -> 0 | T37: =SUM(G36:R36) -> 0 | U37: =SUM(G38:R38) -> 0 | V37: =SUM(T37,U37) -> 0
A38: 35886 | B38: =Input!G$22 -> 0 | E38: 0.12 | F38: Interest amount | G38: =G37/12*$E38 -> 0 | H38: =H37/12*$E38 -> 0 | I38: =I37/12*$E38 -> 0 | J38: =J37/12*$E38 -> 0 | K38: =K37/12*$E38 -> 0 | L38: =L37/12*$E38 -> 0 | M38: =M37/12*$E38 -> 0 | N38: =N37/12*$E38 -> 0 | ... R38: =R37/12*$E38 -> 0 | S38: =SUM(G38:R38) -> 0 | T38: =SUM(T19,T25,T31,T37) -> 0 | U38: =SUM(U19,U25,U31,U37) -> 0 | V38: =SUM(V19,V25,V31,V37) -> 0
A39: 35916 | B39: =Input!H$22 -> 0 | D39: 5 | E39: 1999-2000 | F39: PF'able Salary | G39: 36251 | H39: 36281 | I39: 36312 | J39: 36342 | K39: 36373 | L39: 36404 | M39: 36434 | N39: 36465 | O39: 36495 | P39: 36526 | Q39: 36557 | R39: 36586 | S39: =SUM(Input!G24:R24) -> 0
A40: 35947 | B40: =Input!I$22 -> 0 | F40: 8.33% of PF'able Salary | G40: =IF(Input!G24=0,0,INT((Input!G24*8.33/100)+0.5)) -> 0 | H40: =IF(Input!H24=0,0,INT((Input!H24*8.33/100)+0.5)) -> 0 | I40: =IF(Input!I24=0,0,INT((Input!I24*8.33/100)+0.5)) -> 0 | J40: =IF(Input!J24=0,0,INT((Input!J24*8.33/100)+0.5)) -> 0 | K40: =IF(Input!K24=0,0,INT((Input!K24*8.33/100)+0.5)) -> 0 | L40: =IF(Input!L24=0,0,INT((Input!L24*8.33/100)+0.5)) -> 0 | M40: =IF(Input!M24=0,0,INT((Input!M24*8.33/100)+0.5)) -> 0 | N40: =IF(Input!N24=0,0,INT((Input!N24*8.33/100)+0.5)) -> 0 | ... R40: =IF(Input!R24=0,0,INT((Input!R24*8.33/100)+0.5)) -> 0 | S40: =SUM(G40:R40) -> 0
A41: 35977 | B41: =Input!J$22 -> 0 | F41: Pension contribution (on ceiling) | G41: =IF(Input!G24<=$J$7,INT((Input!G24*8.33%)+0.5),INT(($J$7*8.33%)+0.5)) -> 0 | H41: =IF(Input!H24<=$J$7,INT((Input!H24*8.33%)+0.5),INT(($J$7*8.33%)+0.5)) -> 0 | I41: =IF(Input!I24<=$J$7,INT((Input!I24*8.33%)+0.5),INT(($J$7*8.33%)+0.5)) -> 0 | J41: =IF(Input!J24<=$J$7,INT((Input!J24*8.33%)+0.5),INT(($J$7*8.33%)+0.5)) -> 0 | K41: =IF(Input!K24<=$J$7,INT((Input!K24*8.33%)+0.5),INT(($J$7*8.33%)+0.5)) -> 0 | L41: =IF(Input!L24<=$J$7,INT((Input!L24*8.33%)+0.5),INT(($J$7*8.33%)+0.5)) -> 0 | M41: =IF(Input!M24<=$J$7,INT((Input!M24*8.33%)+0.5),INT(($J$7*8.33%)+0.5)) -> 0 | N41: =IF(Input!N24<=$J$7,INT((Input!N24*8.33%)+0.5),INT(($J$7*8.33%)+0.5)) -> 0 | ... R41: =IF(Input!R24<=$J$7,INT((Input!R24*8.33%)+0.5),INT(($J$7*8.33%)+0.5)) -> 0 | S41: =SUM(G41:R41) -> 0
A42: 36008 | B42: =Input!K$22 -> 0 | F42: Addl Amount Payable on PF'able Salary | G42: =IF(G40-G41<=0,0,G40-G41) -> 0 | H42: =IF(H40-H41<=0,0,H40-H41) -> 0 | I42: =IF(I40-I41<=0,0,I40-I41) -> 0 | J42: =IF(J40-J41<=0,0,J40-J41) -> 0 | K42: =IF(K40-K41<=0,0,K40-K41) -> 0 | L42: =IF(L40-L41<=0,0,L40-L41) -> 0 | M42: =IF(M40-M41<=0,0,M40-M41) -> 0 | N42: =IF(N40-N41<=0,0,N40-N41) -> 0 | ... R42: =IF(R40-R41<=0,0,R40-R41) -> 0 | S42: =SUM(G42:R42) -> 0
A43: 36039 | B43: =Input!L$22 -> 0 | E43: Interest rate | F43: Progressive balance | G43: =IF(G39=0,0,IF($T$11<=Input!G23,0,R36+R37+U37)) -> 0 | H43: =IF(H39=0,0,IF($T$11<=Input!H23,0,G42+G43)) -> 0 | I43: =IF(I39=0,0,IF($T$11<=Input!I23,0,H42+H43)) -> 0 | J43: =IF(J39=0,0,IF($T$11<=Input!J23,0,I42+I43)) -> 0 | K43: =IF(K39=0,0,IF($T$11<=Input!K23,0,J42+J43)) -> 0 | L43: =IF(L39=0,0,IF($T$11<=Input!L23,0,K42+K43)) -> 0 | M43: =IF(M39=0,0,IF($T$11<=Input!M23,0,L42+L43)) -> 0 | N43: =IF(N39=0,0,IF($T$11<=Input!N23,0,M42+M43)) -> 0 | O43: =IF(O39=0,0,IF($T$11<=Input!O23,0,N42+N43)) -> 0 | ... R43: =IF(R39=0,0,IF($T$11<=Input!R23,0,Q42+Q43)) -> 0 | T43: =SUM(G42:R42) -> 0 | U43: =SUM(G44:R44) -> 0 | V43: =SUM(T43,U43) -> 0
A44: 36069 | B44: =Input!M$22 -> 0 | E44: 0.12 | F44: Interest amount | G44: =G43/12*$E44 -> 0 | H44: =H43/12*$E44 -> 0 | I44: =I43/12*$E44 -> 0 | J44: =J43/12*$E44 -> 0 | K44: =K43/12*$E44 -> 0 | L44: =L43/12*$E44 -> 0 | M44: =M43/12*$E44 -> 0 | N44: =N43/12*$E44 -> 0 | ... R44: =R43/12*$E44 -> 0 | S44: =SUM(G44:R44) -> 0 | T44: =SUM(T19,T25,T31,T37,T43) -> 0 | U44: =SUM(U19,U25,U31,U37,U43) -> 0 | V44: =SUM(V19,V25,V31,V37,V43) -> 0
A45: 36100 | B45: =Input!N$22 -> 0 | D45: 6 | E45: 2000-01 | F45: PF'able Salary | G45: 36617 | H45: 36647 | I45: 36678 | J45: 36708 | K45: 36739 | L45: 36770 | M45: 36800 | N45: 36831 | O45: 36861 | P45: 36892 | Q45: 36923 | R45: 36951 | S45: =SUM(Input!G26:R26) -> 0
A46: 36130 | B46: =Input!O$22 -> 0 | F46: 8.33% of PF'able Salary | G46: =IF(Input!G26=0,0,INT((Input!G26*8.33/100)+0.5)) -> 0 | H46: =IF(Input!H26=0,0,INT((Input!H26*8.33/100)+0.5)) -> 0 | I46: =IF(Input!I26=0,0,INT((Input!I26*8.33/100)+0.5)) -> 0 | J46: =IF(Input!J26=0,0,INT((Input!J26*8.33/100)+0.5)) -> 0 | K46: =IF(Input!K26=0,0,INT((Input!K26*8.33/100)+0.5)) -> 0 | L46: =IF(Input!L26=0,0,INT((Input!L26*8.33/100)+0.5)) -> 0 | M46: =IF(Input!M26=0,0,INT((Input!M26*8.33/100)+0.5)) -> 0 | N46: =IF(Input!N26=0,0,INT((Input!N26*8.33/100)+0.5)) -> 0 | ... R46: =IF(Input!R26=0,0,INT((Input!R26*8.33/100)+0.5)) -> 0 | S46: =SUM(G46:R46) -> 0
A47: 36161 | B47: =Input!P$22 -> 0 | E47: Interest rate (Apr ~ June) | F47: Pension contribution (on ceiling) | G47: =IF(Input!G26<=$J$7,INT((Input!G26*8.33%)+0.5),INT(($J$7*8.33%)+0.5)) -> 0 | H47: =IF(Input!H26<=$J$7,INT((Input!H26*8.33%)+0.5),INT(($J$7*8.33%)+0.5)) -> 0 | I47: =IF(Input!I26<=$J$7,INT((Input!I26*8.33%)+0.5),INT(($J$7*8.33%)+0.5)) -> 0 | J47: =IF(Input!J26<=$J$7,INT((Input!J26*8.33%)+0.5),INT(($J$7*8.33%)+0.5)) -> 0 | K47: =IF(Input!K26<=$J$7,INT((Input!K26*8.33%)+0.5),INT(($J$7*8.33%)+0.5)) -> 0 | L47: =IF(Input!L26<=$J$7,INT((Input!L26*8.33%)+0.5),INT(($J$7*8.33%)+0.5)) -> 0 | M47: =IF(Input!M26<=$J$7,INT((Input!M26*8.33%)+0.5),INT(($J$7*8.33%)+0.5)) -> 0 | N47: =IF(Input!N26<=$J$7,INT((Input!N26*8.33%)+0.5),INT(($J$7*8.33%)+0.5)) -> 0 | ... R47: =IF(Input!R26<=$J$7,INT((Input!R26*8.33%)+0.5),INT(($J$7*8.33%)+0.5)) -> 0 | S47: =SUM(G47:R47) -> 0
A48: 36192 | B48: =Input!Q$22 -> 0 | E48: 0.12 | F48: Addl Amount Payable on PF'able Salary | G48: =IF(G46-G47<=0,0,G46-G47) -> 0 | H48: =IF(H46-H47<=0,0,H46-H47) -> 0 | I48: =IF(I46-I47<=0,0,I46-I47) -> 0 | J48: =IF(J46-J47<=0,0,J46-J47) -> 0 | K48: =IF(K46-K47<=0,0,K46-K47) -> 0 | L48: =IF(L46-L47<=0,0,L46-L47) -> 0 | M48: =IF(M46-M47<=0,0,M46-M47) -> 0 | N48: =IF(N46-N47<=0,0,N46-N47) -> 0 | ... R48: =IF(R46-R47<=0,0,R46-R47) -> 0 | S48: =SUM(G48:R48) -> 0
A49: 36220 | B49: =Input!R$22 -> 0 | E49: Interest rate (July onwards) | F49: Progressive balance | G49: =IF(G45=0,0,IF($T$11<=Input!G25,0,R42+R43+U43)) -> 0 | H49: =IF(H45=0,0,IF($T$11<=Input!H25,0,G48+G49)) -> 0 | I49: =IF(I45=0,0,IF($T$11<=Input!I25,0,H48+H49)) -> 0 | J49: =IF(J45=0,0,IF($T$11<=Input!J25,0,I48+I49)) -> 0 | K49: =IF(K45=0,0,IF($T$11<=Input!K25,0,J48+J49)) -> 0 | L49: =IF(L45=0,0,IF($T$11<=Input!L25,0,K48+K49)) -> 0 | M49: =IF(M45=0,0,IF($T$11<=Input!M25,0,L48+L49)) -> 0 | N49: =IF(N45=0,0,IF($T$11<=Input!N25,0,M48+M49)) -> 0 | O49: =IF(O45=0,0,IF($T$11<=Input!O25,0,N48+N49)) -> 0 | ... R49: =IF(R45=0,0,IF($T$11<=Input!R25,0,Q48+Q49)) -> 0 | T49: =SUM(G48:R48) -> 0 | U49: =SUM(G50:R50) -> 0 | V49: =SUM(T49,U49) -> 0
A50: 36251 | B50: =Input!G$24 -> 0 | E50: 0.11 | F50: Interest amount | G50: =G49/12*$E48 -> 0 | H50: =H49/12*$E48 -> 0 | I50: =I49/12*$E48 -> 0 | J50: =J49/12*$E50 -> 0 | K50: =K49/12*$E50 -> 0 | L50: =L49/12*$E50 -> 0 | M50: =M49/12*$E50 -> 0 | N50: =N49/12*$E50 -> 0 | O50: =O49/12*$E50 -> 0 | P50: =P49/12*$E50 -> 0 | Q50: =Q49/12*$E50 -> 0 | R50: =R49/12*$E50 -> 0 | S50: =SUM(G50:R50) -> 0 | T50: =SUM(T19,T25,T31,T37,T43,T49) -> 0 | U50: =SUM(U19,U25,U31,U37,U43,U49) -> 0 | V50: =SUM(V19,V25,V31,V37,V43,V49) -> 0
A51: 36281 | B51: =Input!H$24 -> 0 | D51: 7 | E51: 2001-02 | F51: PF'able Salary | G51: 36982 | H51: 37012 | I51: 37043 | J51: 37073 | K51: 37104 | L51: 37135 | M51: 37165 | N51: 37196 | O51: 37226 | P51: 37257 | Q51: 37288 | R51: 37316 | S51: =SUM(Input!G28:R28) -> 0
A52: 36312 | B52: =Input!I$24 -> 0 | F52: 8.33% of PF'able Salary | G52: =IF(Input!G28=0,0,INT((Input!G28*8.33/100)+0.5)) -> 0 | H52: =IF(Input!H28=0,0,INT((Input!H28*8.33/100)+0.5)) -> 0 | I52: =IF(Input!I28=0,0,INT((Input!I28*8.33/100)+0.5)) -> 0 | J52: =IF(Input!J28=0,0,INT((Input!J28*8.33/100)+0.5)) -> 0 | K52: =IF(Input!K28=0,0,INT((Input!K28*8.33/100)+0.5)) -> 0 | L52: =IF(Input!L28=0,0,INT((Input!L28*8.33/100)+0.5)) -> 0 | M52: =IF(Input!M28=0,0,INT((Input!M28*8.33/100)+0.5)) -> 0 | N52: =IF(Input!N28=0,0,INT((Input!N28*8.33/100)+0.5)) -> 0 | ... R52: =IF(Input!R28=0,0,INT((Input!R28*8.33/100)+0.5)) -> 0 | S52: =SUM(G52:R52) -> 0
A53: 36342 | B53: =Input!J$24 -> 0 | F53: Pension contribution (on ceiling) | G53: =IF(Input!G28<=$J$7,INT((Input!G28*8.33%)+0.5),INT(($J$7*8.33%)+0.5)) -> 0 | H53: =IF(Input!H28<=$J$7,INT((Input!H28*8.33%)+0.5),INT(($J$7*8.33%)+0.5)) -> 0 | I53: =IF(Input!I28<=$J$7,INT((Input!I28*8.33%)+0.5),INT(($J$7*8.33%)+0.5)) -> 0 | J53: =IF(Input!J28<=$P$7,INT((Input!J28*8.33%)+0.5),INT(($P$7*8.33%)+0.5)) -> 0 | K53: =IF(Input!K28<=$P$7,INT((Input!K28*8.33%)+0.5),INT(($P$7*8.33%)+0.5)) -> 0 | L53: =IF(Input!L28<=$P$7,INT((Input!L28*8.33%)+0.5),INT(($P$7*8.33%)+0.5)) -> 0 | M53: =IF(Input!M28<=$P$7,INT((Input!M28*8.33%)+0.5),INT(($P$7*8.33%)+0.5)) -> 0 | N53: =IF(Input!N28<=$P$7,INT((Input!N28*8.33%)+0.5),INT(($P$7*8.33%)+0.5)) -> 0 | O53: =IF(Input!O28<=$P$7,INT((Input!O28*8.33%)+0.5),INT(($P$7*8.33%)+0.5)) -> 0 | P53: =IF(Input!P28<=$P$7,INT((Input!P28*8.33%)+0.5),INT(($P$7*8.33%)+0.5)) -> 0 | Q53: =IF(Input!Q28<=$P$7,INT((Input!Q28*8.33%)+0.5),INT(($P$7*8.33%)+0.5)) -> 0 | R53: =IF(Input!R28<=$P$7,INT((Input!R28*8.33%)+0.5),INT(($P$7*8.33%)+0.5)) -> 0 | S53: =SUM(G53:R53) -> 0
A54: 36373 | B54: =Input!K$24 -> 0 | F54: Addl Amount Payable on PF'able Salary | G54: =IF(G52-G53<=0,0,G52-G53) -> 0 | H54: =IF(H52-H53<=0,0,H52-H53) -> 0 | I54: =IF(I52-I53<=0,0,I52-I53) -> 0 | J54: =IF(J52-J53<=0,0,J52-J53) -> 0 | K54: =IF(K52-K53<=0,0,K52-K53) -> 0 | L54: =IF(L52-L53<=0,0,L52-L53) -> 0 | M54: =IF(M52-M53<=0,0,M52-M53) -> 0 | N54: =IF(N52-N53<=0,0,N52-N53) -> 0 | ... R54: =IF(R52-R53<=0,0,R52-R53) -> 0 | S54: =SUM(G54:R54) -> 0
A55: 36404 | B55: =Input!L$24 -> 0 | E55: Interest rate | F55: Progressive balance | G55: =IF(G51=0,0,IF($T$11<=Input!G27,0,R48+R49+U49)) -> 0 | H55: =IF(H51=0,0,IF($T$11<=Input!H27,0,G54+G55)) -> 0 | I55: =IF(I51=0,0,IF($T$11<=Input!I27,0,H54+H55)) -> 0 | J55: =IF(J51=0,0,IF($T$11<=Input!J27,0,I54+I55)) -> 0 | K55: =IF(K51=0,0,IF($T$11<=Input!K27,0,J54+J55)) -> 0 | L55: =IF(L51=0,0,IF($T$11<=Input!L27,0,K54+K55)) -> 0 | M55: =IF(M51=0,0,IF($T$11<=Input!M27,0,L54+L55)) -> 0 | N55: =IF(N51=0,0,IF($T$11<=Input!N27,0,M54+M55)) -> 0 | O55: =IF(O51=0,0,IF($T$11<=Input!O27,0,N54+N55)) -> 0 | ... R55: =IF(R51=0,0,IF($T$11<=Input!R27,0,Q54+Q55)) -> 0 | T55: =SUM(G54:R54) -> 0 | U55: =SUM(G56:R56) -> 0 | V55: =SUM(T55,U55) -> 0
A56: 36434 | B56: =Input!M$24 -> 0 | E56: 0.095 | F56: Interest amount | G56: =G55/12*$E56 -> 0 | H56: =H55/12*$E56 -> 0 | I56: =I55/12*$E56 -> 0 | J56: =J55/12*$E56 -> 0 | K56: =K55/12*$E56 -> 0 | L56: =L55/12*$E56 -> 0 | M56: =M55/12*$E56 -> 0 | N56: =N55/12*$E56 -> 0 | ... R56: =R55/12*$E56 -> 0 | S56: =SUM(G56:R56) -> 0 | T56: =SUM(T19,T25,T31,T37,T43,T49,T55) -> 0 | U56: =SUM(U19,U25,U31,U37,U43,U49,U55) -> 0 | V56: =SUM(V19,V25,V31,V37,V43,V49,V55) -> 0
A57: 36465 | B57: =Input!N$24 -> 0 | D57: 8 | E57: 2002-03 | F57: PF'able Salary | G57: 37347 | H57: 37377 | I57: 37408 | J57: 37438 | K57: 37469 | L57: 37500 | M57: 37530 | N57: 37561 | O57: 37591 | P57: 37622 | Q57: 37653 | R57: 37681 | S57: =SUM(Input!G30:R30) -> 0
A58: 36495 | B58: =Input!O$24 -> 0 | F58: 8.33% of PF'able Salary | G58: =IF(Input!G30=0,0,INT((Input!G30*8.33/100)+0.5)) -> 0 | H58: =IF(Input!H30=0,0,INT((Input!H30*8.33/100)+0.5)) -> 0 | I58: =IF(Input!I30=0,0,INT((Input!I30*8.33/100)+0.5)) -> 0 | J58: =IF(Input!J30=0,0,INT((Input!J30*8.33/100)+0.5)) -> 0 | K58: =IF(Input!K30=0,0,INT((Input!K30*8.33/100)+0.5)) -> 0 | L58: =IF(Input!L30=0,0,INT((Input!L30*8.33/100)+0.5)) -> 0 | M58: =IF(Input!M30=0,0,INT((Input!M30*8.33/100)+0.5)) -> 0 | N58: =IF(Input!N30=0,0,INT((Input!N30*8.33/100)+0.5)) -> 0 | ... R58: =IF(Input!R30=0,0,INT((Input!R30*8.33/100)+0.5)) -> 0 | S58: =SUM(G58:R58) -> 0
A59: 36526 | B59: =Input!P$24 -> 0 | F59: Pension contribution (on ceiling) | G59: =IF(Input!G30<=$P$7,INT((Input!G30*8.33%)+0.5),INT(($P$7*8.33%)+0.5)) -> 0 | H59: =IF(Input!H30<=$P$7,INT((Input!H30*8.33%)+0.5),INT(($P$7*8.33%)+0.5)) -> 0 | I59: =IF(Input!I30<=$P$7,INT((Input!I30*8.33%)+0.5),INT(($P$7*8.33%)+0.5)) -> 0 | J59: =IF(Input!J30<=$P$7,INT((Input!J30*8.33%)+0.5),INT(($P$7*8.33%)+0.5)) -> 0 | K59: =IF(Input!K30<=$P$7,INT((Input!K30*8.33%)+0.5),INT(($P$7*8.33%)+0.5)) -> 0 | L59: =IF(Input!L30<=$P$7,INT((Input!L30*8.33%)+0.5),INT(($P$7*8.33%)+0.5)) -> 0 | M59: =IF(Input!M30<=$P$7,INT((Input!M30*8.33%)+0.5),INT(($P$7*8.33%)+0.5)) -> 0 | N59: =IF(Input!N30<=$P$7,INT((Input!N30*8.33%)+0.5),INT(($P$7*8.33%)+0.5)) -> 0 | ... R59: =IF(Input!R30<=$P$7,INT((Input!R30*8.33%)+0.5),INT(($P$7*8.33%)+0.5)) -> 0 | S59: =SUM(G59:R59) -> 0
A60: 36557 | B60: =Input!Q$24 -> 0 | F60: Addl Amount Payable on PF'able Salary | G60: =IF(G58-G59<=0,0,G58-G59) -> 0 | H60: =IF(H58-H59<=0,0,H58-H59) -> 0 | I60: =IF(I58-I59<=0,0,I58-I59) -> 0 | J60: =IF(J58-J59<=0,0,J58-J59) -> 0 | K60: =IF(K58-K59<=0,0,K58-K59) -> 0 | L60: =IF(L58-L59<=0,0,L58-L59) -> 0 | M60: =IF(M58-M59<=0,0,M58-M59) -> 0 | N60: =IF(N58-N59<=0,0,N58-N59) -> 0 | ... R60: =IF(R58-R59<=0,0,R58-R59) -> 0 | S60: =SUM(G60:R60) -> 0
A61: 36586 | B61: =Input!R$24 -> 0 | E61: Interest rate | F61: Progressive balance | G61: =IF(G57=0,0,IF($T$11<=Input!G29,0,R54+R55+U55)) -> 0 | H61: =IF(H57=0,0,IF($T$11<=Input!H29,0,G60+G61)) -> 0 | I61: =IF(I57=0,0,IF($T$11<=Input!I29,0,H60+H61)) -> 0 | J61: =IF(J57=0,0,IF($T$11<=Input!J29,0,I60+I61)) -> 0 | K61: =IF(K57=0,0,IF($T$11<=Input!K29,0,J60+J61)) -> 0 | L61: =IF(L57=0,0,IF($T$11<=Input!L29,0,K60+K61)) -> 0 | M61: =IF(M57=0,0,IF($T$11<=Input!M29,0,L60+L61)) -> 0 | N61: =IF(N57=0,0,IF($T$11<=Input!N29,0,M60+M61)) -> 0 | O61: =IF(O57=0,0,IF($T$11<=Input!O29,0,N60+N61)) -> 0 | ... R61: =IF(R57=0,0,IF($T$11<=Input!R29,0,Q60+Q61)) -> 0 | T61: =SUM(G60:R60) -> 0 | U61: =SUM(G62:R62) -> 0 | V61: =SUM(T61,U61) -> 0
A62: 36617 | B62: =Input!G$26 -> 0 | E62: 0.095 | F62: Interest amount | G62: =G61/12*$E62 -> 0 | H62: =H61/12*$E62 -> 0 | I62: =I61/12*$E62 -> 0 | J62: =J61/12*$E62 -> 0 | K62: =K61/12*$E62 -> 0 | L62: =L61/12*$E62 -> 0 | M62: =M61/12*$E62 -> 0 | N62: =N61/12*$E62 -> 0 | ... R62: =R61/12*$E62 -> 0 | S62: =SUM(G62:R62) -> 0 | T62: =SUM(T19,T25,T31,T37,T43,T49,T55,T61) -> 0 | U62: =SUM(U19,U25,U31,U37,U43,U49,U55,U61) -> 0 | V62: =SUM(V19,V25,V31,V37,V43,V49,V55,V61) -> 0
A63: 36647 | B63: =Input!H$26 -> 0 | D63: 9 | E63: 2003-04 | F63: PF'able Salary | G63: 37712 | H63: 37742 | I63: 37773 | J63: 37803 | K63: 37834 | L63: 37865 | M63: 37895 | N63: 37926 | O63: 37956 | P63: 37987 | Q63: 38018 | R63: 38047 | S63: =SUM(Input!G32:R32) -> 0
A64: 36678 | B64: =Input!I$26 -> 0 | F64: 8.33% of PF'able Salary | G64: =IF(Input!G32=0,0,INT((Input!G32*8.33/100)+0.5)) -> 0 | H64: =IF(Input!H32=0,0,INT((Input!H32*8.33/100)+0.5)) -> 0 | I64: =IF(Input!I32=0,0,INT((Input!I32*8.33/100)+0.5)) -> 0 | J64: =IF(Input!J32=0,0,INT((Input!J32*8.33/100)+0.5)) -> 0 | K64: =IF(Input!K32=0,0,INT((Input!K32*8.33/100)+0.5)) -> 0 | L64: =IF(Input!L32=0,0,INT((Input!L32*8.33/100)+0.5)) -> 0 | M64: =IF(Input!M32=0,0,INT((Input!M32*8.33/100)+0.5)) -> 0 | N64: =IF(Input!N32=0,0,INT((Input!N32*8.33/100)+0.5)) -> 0 | ... R64: =IF(Input!R32=0,0,INT((Input!R32*8.33/100)+0.5)) -> 0 | S64: =SUM(G64:R64) -> 0
A65: 36708 | B65: =Input!J$26 -> 0 | F65: Pension contribution (on ceiling) | G65: =IF(Input!G32<=$P$7,INT((Input!G32*8.33%)+0.5),INT(($P$7*8.33%)+0.5)) -> 0 | H65: =IF(Input!H32<=$P$7,INT((Input!H32*8.33%)+0.5),INT(($P$7*8.33%)+0.5)) -> 0 | I65: =IF(Input!I32<=$P$7,INT((Input!I32*8.33%)+0.5),INT(($P$7*8.33%)+0.5)) -> 0 | J65: =IF(Input!J32<=$P$7,INT((Input!J32*8.33%)+0.5),INT(($P$7*8.33%)+0.5)) -> 0 | K65: =IF(Input!K32<=$P$7,INT((Input!K32*8.33%)+0.5),INT(($P$7*8.33%)+0.5)) -> 0 | L65: =IF(Input!L32<=$P$7,INT((Input!L32*8.33%)+0.5),INT(($P$7*8.33%)+0.5)) -> 0 | M65: =IF(Input!M32<=$P$7,INT((Input!M32*8.33%)+0.5),INT(($P$7*8.33%)+0.5)) -> 0 | N65: =IF(Input!N32<=$P$7,INT((Input!N32*8.33%)+0.5),INT(($P$7*8.33%)+0.5)) -> 0 | ... R65: =IF(Input!R32<=$P$7,INT((Input!R32*8.33%)+0.5),INT(($P$7*8.33%)+0.5)) -> 0 | S65: =SUM(G65:R65) -> 0
A66: 36739 | B66: =Input!K$26 -> 0 | F66: Addl Amount Payable on PF'able Salary | G66: =IF(G64-G65<=0,0,G64-G65) -> 0 | H66: =IF(H64-H65<=0,0,H64-H65) -> 0 | I66: =IF(I64-I65<=0,0,I64-I65) -> 0 | J66: =IF(J64-J65<=0,0,J64-J65) -> 0 | K66: =IF(K64-K65<=0,0,K64-K65) -> 0 | L66: =IF(L64-L65<=0,0,L64-L65) -> 0 | M66: =IF(M64-M65<=0,0,M64-M65) -> 0 | N66: =IF(N64-N65<=0,0,N64-N65) -> 0 | ... R66: =IF(R64-R65<=0,0,R64-R65) -> 0 | S66: =SUM(G66:R66) -> 0
A67: 36770 | B67: =Input!L$26 -> 0 | E67: Interest rate | F67: Progressive balance | G67: =IF(G63=0,0,IF($T$11<=Input!G31,0,R60+R61+U61)) -> 0 | H67: =IF(H63=0,0,IF($T$11<=Input!H31,0,G66+G67)) -> 0 | I67: =IF(I63=0,0,IF($T$11<=Input!I31,0,H66+H67)) -> 0 | J67: =IF(J63=0,0,IF($T$11<=Input!J31,0,I66+I67)) -> 0 | K67: =IF(K63=0,0,IF($T$11<=Input!K31,0,J66+J67)) -> 0 | L67: =IF(L63=0,0,IF($T$11<=Input!L31,0,K66+K67)) -> 0 | M67: =IF(M63=0,0,IF($T$11<=Input!M31,0,L66+L67)) -> 0 | N67: =IF(N63=0,0,IF($T$11<=Input!N31,0,M66+M67)) -> 0 | O67: =IF(O63=0,0,IF($T$11<=Input!O31,0,N66+N67)) -> 0 | ... R67: =IF(R63=0,0,IF($T$11<=Input!R31,0,Q66+Q67)) -> 0 | T67: =SUM(G66:R66) -> 0 | U67: =SUM(G68:R68) -> 0 | V67: =SUM(T67,U67) -> 0
A68: 36800 | B68: =Input!M$26 -> 0 | E68: 0.095 | F68: Interest amount | G68: =G67/12*$E68 -> 0 | H68: =H67/12*$E68 -> 0 | I68: =I67/12*$E68 -> 0 | J68: =J67/12*$E68 -> 0 | K68: =K67/12*$E68 -> 0 | L68: =L67/12*$E68 -> 0 | M68: =M67/12*$E68 -> 0 | N68: =N67/12*$E68 -> 0 | ... R68: =R67/12*$E68 -> 0 | S68: =SUM(G68:R68) -> 0 | T68: =SUM(T19,T25,T31,T37,T43,T49,T55,T61,T67) -> 0 | U68: =SUM(U19,U25,U31,U37,U43,U49,U55,U61,U67) -> 0 | V68: =SUM(V19,V25,V31,V37,V43,V49,V55,V61,V67) -> 0
A69: 36831 | B69: =Input!N$26 -> 0 | D69: 10 | E69: 2004-05 | F69: PF'able Salary | G69: 38078 | H69: 38108 | I69: 38139 | J69: 38169 | K69: 38200 | L69: 38231 | M69: 38261 | N69: 38292 | O69: 38322 | P69: 38353 | Q69: 38384 | R69: 38412 | S69: =SUM(Input!G34:R34) -> 0
A70: 36861 | B70: =Input!O$26 -> 0 | F70: 8.33% of PF'able Salary | G70: =IF(Input!G34=0,0,INT((Input!G34*8.33/100)+0.5)) -> 0 | H70: =IF(Input!H34=0,0,INT((Input!H34*8.33/100)+0.5)) -> 0 | I70: =IF(Input!I34=0,0,INT((Input!I34*8.33/100)+0.5)) -> 0 | J70: =IF(Input!J34=0,0,INT((Input!J34*8.33/100)+0.5)) -> 0 | K70: =IF(Input!K34=0,0,INT((Input!K34*8.33/100)+0.5)) -> 0 | L70: =IF(Input!L34=0,0,INT((Input!L34*8.33/100)+0.5)) -> 0 | M70: =IF(Input!M34=0,0,INT((Input!M34*8.33/100)+0.5)) -> 0 | N70: =IF(Input!N34=0,0,INT((Input!N34*8.33/100)+0.5)) -> 0 | ... R70: =IF(Input!R34=0,0,INT((Input!R34*8.33/100)+0.5)) -> 0 | S70: =SUM(G70:R70) -> 0
A71: 36892 | B71: =Input!P$26 -> 0 | F71: Pension contribution (on ceiling) | G71: =IF(Input!G34<=$P$7,INT((Input!G34*8.33%)+0.5),INT(($P$7*8.33%)+0.5)) -> 0 | H71: =IF(Input!H34<=$P$7,INT((Input!H34*8.33%)+0.5),INT(($P$7*8.33%)+0.5)) -> 0 | I71: =IF(Input!I34<=$P$7,INT((Input!I34*8.33%)+0.5),INT(($P$7*8.33%)+0.5)) -> 0 | J71: =IF(Input!J34<=$P$7,INT((Input!J34*8.33%)+0.5),INT(($P$7*8.33%)+0.5)) -> 0 | K71: =IF(Input!K34<=$P$7,INT((Input!K34*8.33%)+0.5),INT(($P$7*8.33%)+0.5)) -> 0 | L71: =IF(Input!L34<=$P$7,INT((Input!L34*8.33%)+0.5),INT(($P$7*8.33%)+0.5)) -> 0 | M71: =IF(Input!M34<=$P$7,INT((Input!M34*8.33%)+0.5),INT(($P$7*8.33%)+0.5)) -> 0 | N71: =IF(Input!N34<=$P$7,INT((Input!N34*8.33%)+0.5),INT(($P$7*8.33%)+0.5)) -> 0 | ... R71: =IF(Input!R34<=$P$7,INT((Input!R34*8.33%)+0.5),INT(($P$7*8.33%)+0.5)) -> 0 | S71: =SUM(G71:R71) -> 0
A72: 36923 | B72: =Input!Q$26 -> 0 | F72: Addl Amount Payable on PF'able Salary | G72: =IF(G70-G71<=0,0,G70-G71) -> 0 | H72: =IF(H70-H71<=0,0,H70-H71) -> 0 | I72: =IF(I70-I71<=0,0,I70-I71) -> 0 | J72: =IF(J70-J71<=0,0,J70-J71) -> 0 | K72: =IF(K70-K71<=0,0,K70-K71) -> 0 | L72: =IF(L70-L71<=0,0,L70-L71) -> 0 | M72: =IF(M70-M71<=0,0,M70-M71) -> 0 | N72: =IF(N70-N71<=0,0,N70-N71) -> 0 | ... R72: =IF(R70-R71<=0,0,R70-R71) -> 0 | S72: =SUM(G72:R72) -> 0
A73: 36951 | B73: =Input!R$26 -> 0 | E73: Interest rate | F73: Progressive balance | G73: =IF(G69=0,0,IF($T$11<=Input!G33,0,R66+R67+U67)) -> 0 | H73: =IF(H69=0,0,IF($T$11<=Input!H33,0,G72+G73)) -> 0 | I73: =IF(I69=0,0,IF($T$11<=Input!I33,0,H72+H73)) -> 0 | J73: =IF(J69=0,0,IF($T$11<=Input!J33,0,I72+I73)) -> 0 | K73: =IF(K69=0,0,IF($T$11<=Input!K33,0,J72+J73)) -> 0 | L73: =IF(L69=0,0,IF($T$11<=Input!L33,0,K72+K73)) -> 0 | M73: =IF(M69=0,0,IF($T$11<=Input!M33,0,L72+L73)) -> 0 | N73: =IF(N69=0,0,IF($T$11<=Input!N33,0,M72+M73)) -> 0 | O73: =IF(O69=0,0,IF($T$11<=Input!O33,0,N72+N73)) -> 0 | ... R73: =IF(R69=0,0,IF($T$11<=Input!R33,0,Q72+Q73)) -> 0 | T73: =SUM(G72:R72) -> 0 | U73: =SUM(G74:R74) -> 0 | V73: =SUM(T73,U73) -> 0
A74: 36982 | B74: =Input!G$28 -> 0 | E74: 0.095 | F74: Interest amount | G74: =G73/12*$E74 -> 0 | H74: =H73/12*$E74 -> 0 | I74: =I73/12*$E74 -> 0 | J74: =J73/12*$E74 -> 0 | K74: =K73/12*$E74 -> 0 | L74: =L73/12*$E74 -> 0 | M74: =M73/12*$E74 -> 0 | N74: =N73/12*$E74 -> 0 | ... R74: =R73/12*$E74 -> 0 | S74: =SUM(G74:R74) -> 0 | T74: =SUM(T19,T25,T31,T37,T43,T49,T55,T61,T67,T73) -> 0 | U74: =SUM(U19,U25,U31,U37,U43,U49,U55,U61,U67,U73) -> 0 | V74: =SUM(V19,V25,V31,V37,V43,V49,V55,V61,V67,V73) -> 0
A75: 37012 | B75: =Input!H$28 -> 0 | D75: 11 | E75: 2005-06 | F75: PF'able Salary | G75: 38443 | H75: 38473 | I75: 38504 | J75: 38534 | K75: 38565 | L75: 38596 | M75: 38626 | N75: 38657 | O75: 38687 | P75: 38718 | Q75: 38749 | R75: 38777 | S75: =SUM(Input!G36:R36) -> 0
A76: 37043 | B76: =Input!I$28 -> 0 | F76: 8.33% of PF'able Salary | G76: =IF(Input!G36=0,0,INT((Input!G36*8.33/100)+0.5)) -> 0 | H76: =IF(Input!H36=0,0,INT((Input!H36*8.33/100)+0.5)) -> 0 | I76: =IF(Input!I36=0,0,INT((Input!I36*8.33/100)+0.5)) -> 0 | J76: =IF(Input!J36=0,0,INT((Input!J36*8.33/100)+0.5)) -> 0 | K76: =IF(Input!K36=0,0,INT((Input!K36*8.33/100)+0.5)) -> 0 | L76: =IF(Input!L36=0,0,INT((Input!L36*8.33/100)+0.5)) -> 0 | M76: =IF(Input!M36=0,0,INT((Input!M36*8.33/100)+0.5)) -> 0 | N76: =IF(Input!N36=0,0,INT((Input!N36*8.33/100)+0.5)) -> 0 | ... R76: =IF(Input!R36=0,0,INT((Input!R36*8.33/100)+0.5)) -> 0 | S76: =SUM(G76:R76) -> 0
A77: 37073 | B77: =Input!J$28 -> 0 | F77: Pension contribution (on ceiling) | G77: =IF(Input!G36<=$P$7,INT((Input!G36*8.33%)+0.5),INT(($P$7*8.33%)+0.5)) -> 0 | H77: =IF(Input!H36<=$P$7,INT((Input!H36*8.33%)+0.5),INT(($P$7*8.33%)+0.5)) -> 0 | I77: =IF(Input!I36<=$P$7,INT((Input!I36*8.33%)+0.5),INT(($P$7*8.33%)+0.5)) -> 0 | J77: =IF(Input!J36<=$P$7,INT((Input!J36*8.33%)+0.5),INT(($P$7*8.33%)+0.5)) -> 0 | K77: =IF(Input!K36<=$P$7,INT((Input!K36*8.33%)+0.5),INT(($P$7*8.33%)+0.5)) -> 0 | L77: =IF(Input!L36<=$P$7,INT((Input!L36*8.33%)+0.5),INT(($P$7*8.33%)+0.5)) -> 0 | M77: =IF(Input!M36<=$P$7,INT((Input!M36*8.33%)+0.5),INT(($P$7*8.33%)+0.5)) -> 0 | N77: =IF(Input!N36<=$P$7,INT((Input!N36*8.33%)+0.5),INT(($P$7*8.33%)+0.5)) -> 0 | ... R77: =IF(Input!R36<=$P$7,INT((Input!R36*8.33%)+0.5),INT(($P$7*8.33%)+0.5)) -> 0 | S77: =SUM(G77:R77) -> 0
A78: 37104 | B78: =Input!K$28 -> 0 | F78: Addl Amount Payable on PF'able Salary | G78: =IF(G76-G77<=0,0,G76-G77) -> 0 | H78: =IF(H76-H77<=0,0,H76-H77) -> 0 | I78: =IF(I76-I77<=0,0,I76-I77) -> 0 | J78: =IF(J76-J77<=0,0,J76-J77) -> 0 | K78: =IF(K76-K77<=0,0,K76-K77) -> 0 | L78: =IF(L76-L77<=0,0,L76-L77) -> 0 | M78: =IF(M76-M77<=0,0,M76-M77) -> 0 | N78: =IF(N76-N77<=0,0,N76-N77) -> 0 | ... R78: =IF(R76-R77<=0,0,R76-R77) -> 0 | S78: =SUM(G78:R78) -> 0
A79: 37135 | B79: =Input!L$28 -> 0 | E79: Interest rate | F79: Progressive balance | G79: =IF(G75=0,0,IF($T$11<=Input!G35,0,R72+R73+U73)) -> 0 | H79: =IF(H75=0,0,IF($T$11<=Input!H35,0,G78+G79)) -> 0 | I79: =IF(I75=0,0,IF($T$11<=Input!I35,0,H78+H79)) -> 0 | J79: =IF(J75=0,0,IF($T$11<=Input!J35,0,I78+I79)) -> 0 | K79: =IF(K75=0,0,IF($T$11<=Input!K35,0,J78+J79)) -> 0 | L79: =IF(L75=0,0,IF($T$11<=Input!L35,0,K78+K79)) -> 0 | M79: =IF(M75=0,0,IF($T$11<=Input!M35,0,L78+L79)) -> 0 | N79: =IF(N75=0,0,IF($T$11<=Input!N35,0,M78+M79)) -> 0 | O79: =IF(O75=0,0,IF($T$11<=Input!O35,0,N78+N79)) -> 0 | ... R79: =IF(R75=0,0,IF($T$11<=Input!R35,0,Q78+Q79)) -> 0 | T79: =SUM(G78:R78) -> 0 | U79: =SUM(G80:R80) -> 0 | V79: =SUM(T79,U79) -> 0
A80: 37165 | B80: =Input!M$28 -> 0 | E80: 0.085 | F80: Interest amount | G80: =G79/12*$E80 -> 0 | H80: =H79/12*$E80 -> 0 | I80: =I79/12*$E80 -> 0 | J80: =J79/12*$E80 -> 0 | K80: =K79/12*$E80 -> 0 | L80: =L79/12*$E80 -> 0 | M80: =M79/12*$E80 -> 0 | N80: =N79/12*$E80 -> 0 | ... R80: =R79/12*$E80 -> 0 | S80: =SUM(G80:R80) -> 0 | T80: =SUM(T19,T25,T31,T37,T43,T49,T55,T61,T67,T73,T79) -> 0 | U80: =SUM(U19,U25,U31,U37,U43,U49,U55,U61,U67,U73,U79) -> 0 | V80: =SUM(V19,V25,V31,V37,V43,V49,V55,V61,V67,V73,V79) -> 0
A81: 37196 | B81: =Input!N$28 -> 0 | D81: 12 | E81: 2006-07 | F81: PF'able Salary | G81: 38808 | H81: 38838 | I81: 38869 | J81: 38899 | K81: 38930 | L81: 38961 | M81: 38991 | N81: 39022 | O81: 39052 | P81: 39083 | Q81: 39114 | R81: 39142 | S81: =SUM(Input!G38:R38) -> 0
A82: 37226 | B82: =Input!O$28 -> 0 | F82: 8.33% of PF'able Salary | G82: =IF(Input!G38=0,0,INT((Input!G38*8.33/100)+0.5)) -> 0 | H82: =IF(Input!H38=0,0,INT((Input!H38*8.33/100)+0.5)) -> 0 | I82: =IF(Input!I38=0,0,INT((Input!I38*8.33/100)+0.5)) -> 0 | J82: =IF(Input!J38=0,0,INT((Input!J38*8.33/100)+0.5)) -> 0 | K82: =IF(Input!K38=0,0,INT((Input!K38*8.33/100)+0.5)) -> 0 | L82: =IF(Input!L38=0,0,INT((Input!L38*8.33/100)+0.5)) -> 0 | M82: =IF(Input!M38=0,0,INT((Input!M38*8.33/100)+0.5)) -> 0 | N82: =IF(Input!N38=0,0,INT((Input!N38*8.33/100)+0.5)) -> 0 | ... R82: =IF(Input!R38=0,0,INT((Input!R38*8.33/100)+0.5)) -> 0 | S82: =SUM(G82:R82) -> 0
A83: 37257 | B83: =Input!P$28 -> 0 | F83: Pension contribution (on ceiling) | G83: =IF(Input!G38<=$P$7,INT((Input!G38*8.33%)+0.5),INT(($P$7*8.33%)+0.5)) -> 0 | H83: =IF(Input!H38<=$P$7,INT((Input!H38*8.33%)+0.5),INT(($P$7*8.33%)+0.5)) -> 0 | I83: =IF(Input!I38<=$P$7,INT((Input!I38*8.33%)+0.5),INT(($P$7*8.33%)+0.5)) -> 0 | J83: =IF(Input!J38<=$P$7,INT((Input!J38*8.33%)+0.5),INT(($P$7*8.33%)+0.5)) -> 0 | K83: =IF(Input!K38<=$P$7,INT((Input!K38*8.33%)+0.5),INT(($P$7*8.33%)+0.5)) -> 0 | L83: =IF(Input!L38<=$P$7,INT((Input!L38*8.33%)+0.5),INT(($P$7*8.33%)+0.5)) -> 0 | M83: =IF(Input!M38<=$P$7,INT((Input!M38*8.33%)+0.5),INT(($P$7*8.33%)+0.5)) -> 0 | N83: =IF(Input!N38<=$P$7,INT((Input!N38*8.33%)+0.5),INT(($P$7*8.33%)+0.5)) -> 0 | ... R83: =IF(Input!R38<=$P$7,INT((Input!R38*8.33%)+0.5),INT(($P$7*8.33%)+0.5)) -> 0 | S83: =SUM(G83:R83) -> 0
A84: 37288 | B84: =Input!Q$28 -> 0 | F84: Addl Amount Payable on PF'able Salary | G84: =IF(G82-G83<=0,0,G82-G83) -> 0 | H84: =IF(H82-H83<=0,0,H82-H83) -> 0 | I84: =IF(I82-I83<=0,0,I82-I83) -> 0 | J84: =IF(J82-J83<=0,0,J82-J83) -> 0 | K84: =IF(K82-K83<=0,0,K82-K83) -> 0 | L84: =IF(L82-L83<=0,0,L82-L83) -> 0 | M84: =IF(M82-M83<=0,0,M82-M83) -> 0 | N84: =IF(N82-N83<=0,0,N82-N83) -> 0 | ... R84: =IF(R82-R83<=0,0,R82-R83) -> 0 | S84: =SUM(G84:R84) -> 0
A85: 37316 | B85: =Input!R$28 -> 0 | E85: Interest rate | F85: Progressive balance | G85: =IF(G81=0,0,IF($T$11<=Input!G37,0,R78+R79+U79)) -> 0 | H85: =IF(H81=0,0,IF($T$11<=Input!H37,0,G84+G85)) -> 0 | I85: =IF(I81=0,0,IF($T$11<=Input!I37,0,H84+H85)) -> 0 | J85: =IF(J81=0,0,IF($T$11<=Input!J37,0,I84+I85)) -> 0 | K85: =IF(K81=0,0,IF($T$11<=Input!K37,0,J84+J85)) -> 0 | L85: =IF(L81=0,0,IF($T$11<=Input!L37,0,K84+K85)) -> 0 | M85: =IF(M81=0,0,IF($T$11<=Input!M37,0,L84+L85)) -> 0 | N85: =IF(N81=0,0,IF($T$11<=Input!N37,0,M84+M85)) -> 0 | O85: =IF(O81=0,0,IF($T$11<=Input!O37,0,N84+N85)) -> 0 | ... R85: =IF(R81=0,0,IF($T$11<=Input!R37,0,Q84+Q85)) -> 0 | T85: =SUM(G84:R84) -> 0 | U85: =SUM(G86:R86) -> 0 | V85: =SUM(T85,U85) -> 0
A86: 37347 | B86: =Input!G$30 -> 0 | E86: 0.085 | F86: Interest amount | G86: =G85/12*$E86 -> 0 | H86: =H85/12*$E86 -> 0 | I86: =I85/12*$E86 -> 0 | J86: =J85/12*$E86 -> 0 | K86: =K85/12*$E86 -> 0 | L86: =L85/12*$E86 -> 0 | M86: =M85/12*$E86 -> 0 | N86: =N85/12*$E86 -> 0 | ... R86: =R85/12*$E86 -> 0 | S86: =SUM(G86:R86) -> 0 | T86: =SUM(T19,T25,T31,T37,T43,T49,T55,T61,T67,T73,T79,T85) -> 0 | U86: =SUM(U19,U25,U31,U37,U43,U49,U55,U61,U67,U73,U79,U85) -> 0 | V86: =SUM(V19,V25,V31,V37,V43,V49,V55,V61,V67,V73,V79,V85) -> 0
A87: 37377 | B87: =Input!H$30 -> 0 | D87: 13 | E87: 2007-08 | F87: PF'able Salary | G87: 39173 | H87: 39203 | I87: 39234 | J87: 39264 | K87: 39295 | L87: 39326 | M87: 39356 | N87: 39387 | O87: 39417 | P87: 39448 | Q87: 39479 | R87: 39508 | S87: =SUM(Input!G40:R40) -> 0
A88: 37408 | B88: =Input!I$30 -> 0 | F88: 8.33% of PF'able Salary | G88: =IF(Input!G40=0,0,INT((Input!G40*8.33/100)+0.5)) -> 0 | H88: =IF(Input!H40=0,0,INT((Input!H40*8.33/100)+0.5)) -> 0 | I88: =IF(Input!I40=0,0,INT((Input!I40*8.33/100)+0.5)) -> 0 | J88: =IF(Input!J40=0,0,INT((Input!J40*8.33/100)+0.5)) -> 0 | K88: =IF(Input!K40=0,0,INT((Input!K40*8.33/100)+0.5)) -> 0 | L88: =IF(Input!L40=0,0,INT((Input!L40*8.33/100)+0.5)) -> 0 | M88: =IF(Input!M40=0,0,INT((Input!M40*8.33/100)+0.5)) -> 0 | N88: =IF(Input!N40=0,0,INT((Input!N40*8.33/100)+0.5)) -> 0 | ... R88: =IF(Input!R40=0,0,INT((Input!R40*8.33/100)+0.5)) -> 0 | S88: =SUM(G88:R88) -> 0
A89: 37438 | B89: =Input!J$30 -> 0 | F89: Pension contribution (on ceiling) | G89: =IF(Input!G40<=$P$7,INT((Input!G40*8.33%)+0.5),INT(($P$7*8.33%)+0.5)) -> 0 | H89: =IF(Input!H40<=$P$7,INT((Input!H40*8.33%)+0.5),INT(($P$7*8.33%)+0.5)) -> 0 | I89: =IF(Input!I40<=$P$7,INT((Input!I40*8.33%)+0.5),INT(($P$7*8.33%)+0.5)) -> 0 | J89: =IF(Input!J40<=$P$7,INT((Input!J40*8.33%)+0.5),INT(($P$7*8.33%)+0.5)) -> 0 | K89: =IF(Input!K40<=$P$7,INT((Input!K40*8.33%)+0.5),INT(($P$7*8.33%)+0.5)) -> 0 | L89: =IF(Input!L40<=$P$7,INT((Input!L40*8.33%)+0.5),INT(($P$7*8.33%)+0.5)) -> 0 | M89: =IF(Input!M40<=$P$7,INT((Input!M40*8.33%)+0.5),INT(($P$7*8.33%)+0.5)) -> 0 | N89: =IF(Input!N40<=$P$7,INT((Input!N40*8.33%)+0.5),INT(($P$7*8.33%)+0.5)) -> 0 | ... R89: =IF(Input!R40<=$P$7,INT((Input!R40*8.33%)+0.5),INT(($P$7*8.33%)+0.5)) -> 0 | S89: =SUM(G89:R89) -> 0
A90: 37469 | B90: =Input!K$30 -> 0 | F90: Addl Amount Payable on PF'able Salary | G90: =IF(G88-G89<=0,0,G88-G89) -> 0 | H90: =IF(H88-H89<=0,0,H88-H89) -> 0 | I90: =IF(I88-I89<=0,0,I88-I89) -> 0 | J90: =IF(J88-J89<=0,0,J88-J89) -> 0 | K90: =IF(K88-K89<=0,0,K88-K89) -> 0 | L90: =IF(L88-L89<=0,0,L88-L89) -> 0 | M90: =IF(M88-M89<=0,0,M88-M89) -> 0 | N90: =IF(N88-N89<=0,0,N88-N89) -> 0 | ... R90: =IF(R88-R89<=0,0,R88-R89) -> 0 | S90: =SUM(G90:R90) -> 0
A91: 37500 | B91: =Input!L$30 -> 0 | E91: Interest rate | F91: Progressive balance | G91: =IF(G87=0,0,IF($T$11<=Input!G39,0,R84+R85+U85)) -> 0 | H91: =IF(H87=0,0,IF($T$11<=Input!H39,0,G90+G91)) -> 0 | I91: =IF(I87=0,0,IF($T$11<=Input!I39,0,H90+H91)) -> 0 | J91: =IF(J87=0,0,IF($T$11<=Input!J39,0,I90+I91)) -> 0 | K91: =IF(K87=0,0,IF($T$11<=Input!K39,0,J90+J91)) -> 0 | L91: =IF(L87=0,0,IF($T$11<=Input!L39,0,K90+K91)) -> 0 | M91: =IF(M87=0,0,IF($T$11<=Input!M39,0,L90+L91)) -> 0 | N91: =IF(N87=0,0,IF($T$11<=Input!N39,0,M90+M91)) -> 0 | O91: =IF(O87=0,0,IF($T$11<=Input!O39,0,N90+N91)) -> 0 | ... R91: =IF(R87=0,0,IF($T$11<=Input!R39,0,Q90+Q91)) -> 0 | T91: =SUM(G90:R90) -> 0 | U91: =SUM(G92:R92) -> 0 | V91: =SUM(T91,U91) -> 0
A92: 37530 | B92: =Input!M$30 -> 0 | E92: 0.085 | F92: Interest amount | G92: =G91/12*$E92 -> 0 | H92: =H91/12*$E92 -> 0 | I92: =I91/12*$E92 -> 0 | J92: =J91/12*$E92 -> 0 | K92: =K91/12*$E92 -> 0 | L92: =L91/12*$E92 -> 0 | M92: =M91/12*$E92 -> 0 | N92: =N91/12*$E92 -> 0 | ... R92: =R91/12*$E92 -> 0 | S92: =SUM(G92:R92) -> 0 | T92: =SUM(T19,T25,T31,T37,T43,T49,T55,T61,T67,T73,T79,T85,T91) -> 0 | U92: =SUM(U19,U25,U31,U37,U43,U49,U55,U61,U67,U73,U79,U85,U91) -> 0 | V92: =SUM(V19,V25,V31,V37,V43,V49,V55,V61,V67,V73,V79,V85,V91) -> 0
A93: 37561 | B93: =Input!N$30 -> 0 | D93: 14 | E93: 2008-09 | F93: PF'able Salary | G93: 39539 | H93: 39569 | I93: 39600 | J93: 39630 | K93: 39661 | L93: 39692 | M93: 39722 | N93: 39753 | O93: 39783 | P93: 39814 | Q93: 39845 | R93: 39873 | S93: =SUM(Input!G42:R42) -> 174178
A94: 37591 | B94: =Input!O$30 -> 0 | F94: 8.33% of PF'able Salary | G94: =IF(Input!G42=0,0,INT((Input!G42*8.33/100)+0.5)) -> 0 | H94: =IF(Input!H42=0,0,INT((Input!H42*8.33/100)+0.5)) -> 0 | I94: =IF(Input!I42=0,0,INT((Input!I42*8.33/100)+0.5)) -> 0 | J94: =IF(Input!J42=0,0,INT((Input!J42*8.33/100)+0.5)) -> 0 | K94: =IF(Input!K42=0,0,INT((Input!K42*8.33/100)+0.5)) -> 0 | L94: =IF(Input!L42=0,0,INT((Input!L42*8.33/100)+0.5)) -> 0 | M94: =IF(Input!M42=0,0,INT((Input!M42*8.33/100)+0.5)) -> 0 | N94: =IF(Input!N42=0,0,INT((Input!N42*8.33/100)+0.5)) -> 0 | ... R94: =IF(Input!R42=0,0,INT((Input!R42*8.33/100)+0.5)) -> 14509 | S94: =SUM(G94:R94) -> 14509
A95: 37622 | B95: =Input!P$30 -> 0 | F95: Pension contribution (on ceiling) | G95: =IF(Input!G42<=$P$7,INT((Input!G42*8.33%)+0.5),INT(($P$7*8.33%)+0.5)) -> 0 | H95: =IF(Input!H42<=$P$7,INT((Input!H42*8.33%)+0.5),INT(($P$7*8.33%)+0.5)) -> 0 | I95: =IF(Input!I42<=$P$7,INT((Input!I42*8.33%)+0.5),INT(($P$7*8.33%)+0.5)) -> 0 | J95: =IF(Input!J42<=$P$7,INT((Input!J42*8.33%)+0.5),INT(($P$7*8.33%)+0.5)) -> 0 | K95: =IF(Input!K42<=$P$7,INT((Input!K42*8.33%)+0.5),INT(($P$7*8.33%)+0.5)) -> 0 | L95: =IF(Input!L42<=$P$7,INT((Input!L42*8.33%)+0.5),INT(($P$7*8.33%)+0.5)) -> 0 | M95: =IF(Input!M42<=$P$7,INT((Input!M42*8.33%)+0.5),INT(($P$7*8.33%)+0.5)) -> 0 | N95: =IF(Input!N42<=$P$7,INT((Input!N42*8.33%)+0.5),INT(($P$7*8.33%)+0.5)) -> 0 | ... R95: =IF(Input!R42<=$P$7,INT((Input!R42*8.33%)+0.5),INT(($P$7*8.33%)+0.5)) -> 541 | S95: =SUM(G95:R95) -> 541
A96: 37653 | B96: =Input!Q$30 -> 0 | F96: Addl Amount Payable on PF'able Salary | G96: =IF(G94-G95<=0,0,G94-G95) -> 0 | H96: =IF(H94-H95<=0,0,H94-H95) -> 0 | I96: =IF(I94-I95<=0,0,I94-I95) -> 0 | J96: =IF(J94-J95<=0,0,J94-J95) -> 0 | K96: =IF(K94-K95<=0,0,K94-K95) -> 0 | L96: =IF(L94-L95<=0,0,L94-L95) -> 0 | M96: =IF(M94-M95<=0,0,M94-M95) -> 0 | N96: =IF(N94-N95<=0,0,N94-N95) -> 0 | ... R96: =IF(R94-R95<=0,0,R94-R95) -> 13968 | S96: =SUM(G96:R96) -> 13968
A97: 37681 | B97: =Input!R$30 -> 0 | E97: Interest rate | F97: Progressive balance | G97: =IF(G93=0,0,IF($T$11<=Input!G41,0,R90+R91+U91)) -> 0 | H97: =IF(H93=0,0,IF($T$11<=Input!H41,0,G96+G97)) -> 0 | I97: =IF(I93=0,0,IF($T$11<=Input!I41,0,H96+H97)) -> 0 | J97: =IF(J93=0,0,IF($T$11<=Input!J41,0,I96+I97)) -> 0 | K97: =IF(K93=0,0,IF($T$11<=Input!K41,0,J96+J97)) -> 0 | L97: =IF(L93=0,0,IF($T$11<=Input!L41,0,K96+K97)) -> 0 | M97: =IF(M93=0,0,IF($T$11<=Input!M41,0,L96+L97)) -> 0 | N97: =IF(N93=0,0,IF($T$11<=Input!N41,0,M96+M97)) -> 0 | O97: =IF(O93=0,0,IF($T$11<=Input!O41,0,N96+N97)) -> 0 | ... R97: =IF(R93=0,0,IF($T$11<=Input!R41,0,Q96+Q97)) -> 0 | T97: =SUM(G96:R96) -> 13968 | U97: =SUM(G98:R98) -> 0 | V97: =SUM(T97,U97) -> 13968
A98: 37712 | B98: =Input!G$32 -> 0 | E98: 0.085 | F98: Interest amount | G98: =G97/12*$E98 -> 0 | H98: =H97/12*$E98 -> 0 | I98: =I97/12*$E98 -> 0 | J98: =J97/12*$E98 -> 0 | K98: =K97/12*$E98 -> 0 | L98: =L97/12*$E98 -> 0 | M98: =M97/12*$E98 -> 0 | N98: =N97/12*$E98 -> 0 | ... R98: =R97/12*$E98 -> 0 | S98: =SUM(G98:R98) -> 0 | T98: =SUM(T19,T25,T31,T37,T43,T49,T55,T61,T67,T73,T79,T85,T91,T97) -> 13968 | U98: =SUM(U19,U25,U31,U37,U43,U49,U55,U61,U67,U73,U79,U85,U91,U97) -> 0 | V98: =SUM(V19,V25,V31,V37,V43,V49,V55,V61,V67,V73,V79,V85,V91,V97) -> 13968
A99: 37742 | B99: =Input!H$32 -> 0 | D99: 15 | E99: 2009-10 | F99: PF'able Salary | G99: 39904 | H99: 39934 | I99: 39965 | J99: 39995 | K99: 40026 | L99: 40057 | M99: 40087 | N99: 40118 | O99: 40148 | P99: 40179 | Q99: 40210 | R99: 40238 | S99: =SUM(Input!G44:R44) -> 369267
A100: 37773 | B100: =Input!I$32 -> 0 | F100: 8.33% of PF'able Salary | G100: =IF(Input!G44=0,0,INT((Input!G44*8.33/100)+0.5)) -> 2413 | H100: =IF(Input!H44=0,0,INT((Input!H44*8.33/100)+0.5)) -> 2413 | I100: =IF(Input!I44=0,0,INT((Input!I44*8.33/100)+0.5)) -> 2650 | J100: =IF(Input!J44=0,0,INT((Input!J44*8.33/100)+0.5)) -> 2486 | K100: =IF(Input!K44=0,0,INT((Input!K44*8.33/100)+0.5)) -> 2486 | L100: =IF(Input!L44=0,0,INT((Input!L44*8.33/100)+0.5)) -> 2486 | M100: =IF(Input!M44=0,0,INT((Input!M44*8.33/100)+0.5)) -> 2588 | N100: =IF(Input!N44=0,0,INT((Input!N44*8.33/100)+0.5)) -> 2588 | ... R100: =IF(Input!R44=0,0,INT((Input!R44*8.33/100)+0.5)) -> 2587 | S100: =SUM(G100:R100) -> 30763
...

Sheet Output & Statistics
B2: EPS 1995 Pension - Output & Statistics (Ratios)
B3: Developed by Mr. Neeraj Bhargava (9950826109) in consultation with Mr. Parveen Kohli (9810306699) & with technical support from Mr. C Ramasamy
B5: Name | H5: :: | I5: =Input!K8 -> VARRINDER KAUR RAINA
B6: Date of Commencement of Ceiling Salary Pension | H6: :: | I6: =Input!I11 -> 43586
B7: Date of Commencement of Actual Salary Pension | H7: :: | I7: =Input!O11 -> 43586
B9: Output | I9: Statistics (Ratios)
B11: Superannuated Pension | C11: Amount type | D11: From | E11: To | F11: S No | G11: Amount in Rs. | I11: Ratios | J11: S No | K11: Value
C12: Ceiling Salary Pension | F12: 1 | G12: =IF('Pension Cal'!Q32=0,'Pension Cal'!M46,0) -> 3531 | I12: Increase in Pension Amount (in numbers) | J12: 2/1 | K12: =IF('Pension Cal'!Q32<=0,G13/G12,0) -> 6.8408383
C13: Actual Salary Pension | F13: 2 | G13: =IF('Pension Cal'!Q32=0,'Pension Cal'!R46,0) -> 24155 | I13: Difference between Proposed commencement of actual salary pension and Start of ceiling salary pension (in months) | J13: 9 | K13: =IF('Pension Cal'!Q32<=0,('Amount Cal'!T11-'Amount Cal'!I11)/30,0) -> -1.0333333
C14: Increase in Pension (Difference in Actual Salary & Ceiling Amount Pension) | F14: 2-1 | G14: =G13-G12 -> 20624
C16: Differential contribution | D16: =IF(G12=0,0,'Pension Cal'!F9) -> 35019 | E16: =IF(G12=0,0,'Amount Cal'!G11) -> 43586 | F16: 3 | G16: =IF(G12=0,0,MAX('Amount Cal'!T20:T198)) -> 691316.26 | I16: Differential contribution / Differential contribution with total interest (in %) | J16: 3/3+6 | K16: =IF('Pension Cal'!Q32<=0,G16/G21,0) -> 0.74902544
C17: Additional amount Paid for 1.16% Govt share after 01-09-2014 | D17: =IF(G12=0,0,'Pension Cal'!F11) -> 41883 | E17: =IF(G12=0,0,'Amount Cal'!G11) -> 43586 | F17: 4 | G17: =IF(AND(G12=0,Input!I10>'Pension Cal'!F11),0,SUM('Amount Cal'!S132,'Amount Cal'!S139,'Amount Cal'!S146,'Amount Cal'!S153,'Amount Cal'!S160,'Amount Cal'!S174,'Amount Cal'!S181,'Amount Cal'!S188,'Amount Cal'!S195)) -> 54507 | I17: Additional amount / Differential contribution with total interest (in %) | J17: 4/3+6 | K17: =IF('Pension Cal'!Q32<=0,G17/G21,0) -> 0.059057094
C18: Interest on differential contribution | D18: =IF(G12=0,0,'Pension Cal'!F9) -> 35019 | E18: =IF(G12=0,0,'Amount Cal'!G11) -> 43586 | F18: 5 | G18: =IF(G12=0,0,VLOOKUP((MAX('Amount Cal'!T20:'Amount Cal'!T191)),('Amount Cal'!T20:'Amount Cal'!U198),2,FALSE)) -> 231638.05 | I18: Interest till date of retirement / Differential contribution with total interest (in %) | J18: 5/3+6 | K18: =IF('Pension Cal'!Q32<=0,G18/G21,0) -> 0.25097456
C19: Interest on differential contribution & interest | D19: =IF(G12=0,0,'Amount Cal'!I11) -> 43617 | E19: =IF(G12=0,0,I7) -> 43586 | F19: 5-6 | G19: =G20-G18 -> 0 | I19: Interest on differential contribution & interest / Differential contribution with total interest (in %) | J19: 5-6/3+6 | K19: =IF('Pension Cal'!Q32<=0,G19/G21,0) -> 0
C20: Total Interest | D20: =IF(G12=0,0,'Pension Cal'!F9) -> 35019 | E20: =IF(G12=0,0,I7) -> 43586 | F20: 6 | G20: =IF(G12=0,0,MAX('Amount Cal'!U20:'Amount Cal'!U191)) -> 231638.05 | I20: Total Interest / Differential contribution with total Interest (in %) | J20: 6/3+6 | K20: =IF('Pension Cal'!Q32<=0,G20/G21,0) -> 0.25097456
C21: Differential Contribution with Total Interest | F21: 3+6 | G21: =SUM(G16,G20) -> 922954.31
C22: Total to pay to EPFO | F22: 4+3+6 | G22: =SUM(G17,G21) -> 977461.31
C24: Pension Revision Arrear (without interest) | F24: 7 | G24: =IF(G12=0,0,G14*K13) -> -21311.467 | I24: Balance amount will be recovered (in months) * | J24: 3+6-7/ 2-1 | K24: =IF(G21-G24<=0,0,INT(G21-G24)/G14) -> 45.784765
I25: Pension Arrear / Payment to EPFO (in numbers) | J25: 7/ 4+3+6 | K25: =IF('Pension Cal'!Q32<=0,G24/G22,0) -> -0.021802875
C27: Average 12/60 months salary | F27: 8 | G27: =IF(G12=0,0,IF(Input!I10<'Pension Cal'!F11,'Pension Cal'!V37,'Pension Cal'!W37)) -> 86909.967 | I27: Actual Salary Pension / 60 months average salary (in %) | J27: 2/8 | K27: =IF(G12=0,0,G13/G27) -> 0.2779313
I28: Differential contribution with Interest / 60 months average salary (in numbers) | J28: 3+6/8 | K28: =IF(G12=0,0,G21/G27) -> 10.61966
I29: Pension Revision Arrears without interest / 60 months average salary (in numbers) ** | J29: 7/8 | K29: =IF(G12=0,0,G24/G27) -> -0.24521315
B31: Reduceded Pension | C31: Amount type | D31: From | E31: To | F31: S No | G31: Amount in Rs. | I31: Ratios | J31: S No | K31: Value
C32: Ceiling Salary Pension | F32: 1 | G32: =IF('Pension Cal'!I13<'Pension Cal'!I12,'Pension Cal'!M51,0) -> 0 | I32: Increase in Pension Amount (in numbers) | J32: 2/1 | K32: =IF(G32=0,0,G33/G32) -> 0
C33: Actual Salary Pension | F33: 2 | G33: =IF('Pension Cal'!I13<'Pension Cal'!I12,'Pension Cal'!R51,0) -> 0 | I33: Difference between Proposed commencement of actual salary pension and Start of ceiling salary pension (in months) | J33: 9 | K33: =IF(G32=0,0,('Amount Cal'!T11-'Amount Cal'!I11)/30) -> 0
C34: Increase in Pension (Difference in Actual Salary & Ceiling Amount Pension) | F34: 2-1 | G34: =G33-G32 -> 0
C36: Differential contribution | D36: =IF(G32=0,0,'Pension Cal'!F9) -> 0 | E36: =IF(G32=0,0,'Amount Cal'!M11) -> 0 | F36: 3 | G36: =IF(G32=0,0,MAX('Amount Cal'!T20:T198)) -> 0 | I36: Differential contribution / Differential contribution with interest (in %) | J36: 3/3+6 | K36: =IF(G32=0,0,G36/G41) -> 0
C37: Additional amount Paid for 1.16% Govt share after 01-09-2014 | D37: =IF(G32=0,0,'Pension Cal'!F11) -> 0 | E37: =IF(G32=0,0,'Amount Cal'!T11) -> 0 | F37: 4 | G37: =IF(AND(G32=0,Input!I10>'Pension Cal'!F11),0,SUM('Amount Cal'!S132,'Amount Cal'!S139,'Amount Cal'!S146,'Amount Cal'!S153,'Amount Cal'!S160,'Amount Cal'!S174,'Amount Cal'!S181,'Amount Cal'!S188,'Amount Cal'!S195)) -> 0 | I37: Additional amount / Differential contribution with interest (in %) | J37: 4/3+6 | K37: =IF(G32=0,0,G37/G41) -> 0
C38: Interest on differential contribution | D38: =IF(G32=0,0,'Pension Cal'!F9) -> 0 | E38: =IF(G32=0,0,'Amount Cal'!M11) -> 0 | F38: 5 | G38: =IF(G32=0,0,VLOOKUP((MAX('Amount Cal'!T20:'Amount Cal'!T198)),('Amount Cal'!T20:'Amount Cal'!U198),2,FALSE)) -> 0 | I38: Interest till date of retirement / Differential contribution with interest (in %) | J38: 5/3+6 | K38: =IF(G32=0,0,G38/G41) -> 0
C39: Interest on differential contribution & interest | D39: =IF(G32=0,0,'Amount Cal'!O11) -> 0 | E39: =IF(G32=0,0,I29) -> 0 | F39: 5-6 | G39: =G40-G38 -> 0 | I39: Differential contribution / Differential contribution with interest (in %) | J39: 5-6/3+6 | K39: =IF(G32=0,0,G39/G41) -> 0
C40: Total Interest | D40: =IF(G32=0,0,'Pension Cal'!F9) -> 0 | E40: =IF(G32=0,0,I29) -> 0 | F40: 6 | G40: =IF(G32=0,0,MAX('Amount Cal'!U20:'Amount Cal'!U198)) -> 0 | I40: Total Interest / Differential contribution with Interest (in %) | J40: 6/3+6 | K40: =IF(G32=0,0,G40/G41) -> 0
C41: Differential contribution with Interest | F41: 3+6 | G41: =SUM(G36,G40) -> 0
C42: Total to pay to EPFO | F42: 4+3+6 | G42: =SUM(G37,G41) -> 0
C44: Pension Revision Arrear (without interest) | F44: 7 | G44: =IF(G32=0,0,G34*K33) -> 0 | I44: Balance amount will be recovered (in months) * | J44: 3+6-7/ 2-1 | K44: =IF(G41-G44<=0,0,INT(G41-G44)/G34) -> 0
I45: Pension Arrear / Payment to EPFO (in numbers) | J45: 7/ 4+3+6 | K45: =IF(G32=0,0,G44/G42) -> 0
C47: Average 12/60 months salary | F47: 8 | G47: =IF(G32=0,0,IF(Input!I10<'Pension Cal'!F11,'Pension Cal'!V37,'Pension Cal'!W37)) -> 0 | I47: Actual Salary Pension / 60 months average salary (in %) | J47: 2/8 | K47: =IF(G32=0,0,G33/G47) -> 0
I48: Differential contribution with Interest / 60 months average salary (in numbers) | J48: 3+6/8 | K48: =IF(G32=0,0,G41/G47) -> 0
I49: Pension Revision Arrears without interest / 60 months average salary (in numbers) ** | J49: 7/8 | K49: =IF(G32=0,0,G44/G47) -> 0
B51: Enhanced Pension | C51: Amount type | F51: S No | G51: Amount in Rs. | I51: Ratios | J51: S No | K51: Value
C52: Ceiling Salary Pension | F52: 1 | G52: =IF('Pension Cal'!I13<'Pension Cal'!I12,0,'Pension Cal'!M52) -> 0 | I52: Increase in Pension Amount (in numbers) | J52: 2/1 | K52: =IF(G52=0,0,G53/G52) -> 0
C53: Actual Salary Pension | F53: 2 | G53: =IF('Pension Cal'!I13<'Pension Cal'!I12,0,'Pension Cal'!R52) -> 0 | I53: Difference between Proposed commencement of actual salary pension and Start of ceiling salary pension (in months) | J53: 9 | K53: =IF(G52=0,0,('Amount Cal'!T11-'Amount Cal'!I11)/30) -> 0
C54: Increase in Pension (Difference in Actual Salary & Ceiling Amount Pension) | F54: 2-1 | G54: =G53-G52 -> 0
C56: Differential contribution | D56: =IF(G52=0,0,'Pension Cal'!F9) -> 0 | E56: =IF(G52=0,0,'Amount Cal'!M11) -> 0 | F56: 3 | G56: =IF(G52=0,0,MAX('Amount Cal'!T20:T198)) -> 0 | I56: Differential contribution / Differential contribution with interest (in %) | J56: 3/3+6 | K56: =IF(G52=0,0,G56/G61) -> 0
C57: Additional amount Paid for 1.16% Govt share after 01-09-2014 | D57: =IF(G52=0,0,'Pension Cal'!F11) -> 0 | E57: =IF(G52=0,0,'Amount Cal'!T11) -> 0 | F57: 4 | G57: =IF(AND(G52=0,Input!I10>'Pension Cal'!F11),0,SUM('Amount Cal'!S132,'Amount Cal'!S139,'Amount Cal'!S146,'Amount Cal'!S153,'Amount Cal'!S160,'Amount Cal'!S174,'Amount Cal'!S181,'Amount Cal'!S188,'Amount Cal'!S195)) -> 0 | I57: Additional amount / Differential contribution with interest (in %) | J57: 4/3+6 | K57: =IF(G52=0,0,G57/G61) -> 0
C58: Interest on differential contribution | D58: =IF(G52=0,0,'Pension Cal'!F9) -> 0 | E58: =IF(G52=0,0,'Amount Cal'!M11) -> 0 | F58: 5 | G58: =IF(G52=0,0,VLOOKUP((MAX('Amount Cal'!T20:'Amount Cal'!T198)),('Amount Cal'!T20:'Amount Cal'!U198),2,FALSE)) -> 0 | I58: Interest till date of retirement / Differential contribution with interest (in %) | J58: 5/3+6 | K58: =IF(G52=0,0,G58/G61) -> 0
C59: Interest on differential contribution & interest | D59: =IF(G52=0,0,'Amount Cal'!O11) -> 0 | E59: =IF(G52=0,0,'Amount Cal'!T11) -> 0 | F59: 5-6 | G59: =G60-G58 -> 0 | I59: Differential contribution / Differential contribution with interest (in %) | J59: 5-6/3+6 | K59: =IF(G52=0,0,G59/G61) -> 0
C60: Total Interest | D60: =IF(G52=0,0,'Pension Cal'!F9) -> 0 | E60: =IF(G52=0,0,'Amount Cal'!T11) -> 0 | F60: 6 | G60: =IF(G52=0,0,MAX('Amount Cal'!U20:'Amount Cal'!U198)) -> 0 | I60: Total Interest / Differential contribution with Interest (in %) | J60: 6/3+6 | K60: =IF(G52=0,0,G60/G61) -> 0
C61: Differential contribution with Interest | F61: 3+6 | G61: =SUM(G56,G60) -> 0
C62: Total to pay to EPFO | F62: 4+3+6 | G62: =SUM(G57,G61) -> 0
C64: Pension Revision Arrear (without interest) | F64: 7 | G64: =IF(G52=0,0,G54*K53) -> 0 | I64: Balance amount will be recovered (in months) * | J64: 3+6-7/ 2-1 | K64: =IF(G61-G64<=0,0,INT(G61-G64)/G54) -> 0
I65: Pension Arrear / Payment to EPFO (in numbers) | J65: 7/ 4+3+6 | K65: =IF(G52=0,0,G64/G62) -> 0
C67: Average 12/60 months salary | F67: 8 | G67: =IF(G52=0,0,IF(Input!I10<'Pension Cal'!F11,'Pension Cal'!V37,'Pension Cal'!W37)) -> 0 | I67: Actual Salary Pension / 60 months average salary (in %) | J67: 2/8 | K67: =IF(G52=0,0,G53/G67) -> 0
I68: Differential contribution with Interest / 60 months average salary (in numbers) | J68: 3+6/8 | K68: =IF(G52=0,0,G61/G67) -> 0
I69: Pension Revision Arrears without interest / 60 months average salary (in numbers) ** | J69: 7/8 | K69: =IF(G52=0,0,G64/G67) -> 0
B71: * If Pension arrear is less than differential amount plus interest and if adjustment is permitted by EPFO
B72: ** If ROC, Commutation etc., reduction factors are not applicable
